{
    "PlayerInfo": {
        "n_ActionID": 13544752,
        "n_ActionSet": 4,
        "n_ActionSort": 7,
        "n_StartPeriodSort": 1,
        "n_StartTime": null,
        "n_EndPeriodSort": 4,
        "n_EndTime": 3826000,
        "n_HomeOrAway": 1,
        "n_TeamID": 61,
        "c_Team": "AZ",
        "c_TeamShort": "AZ",
        "n_PersonID": 807475,
        "c_Person": "Celso Ortíz",
        "c_PersonSort": "Ortíz, Celso",
        "c_PersonShort": "Ortíz",
        "c_PersonFirstName": "Celso",
        "c_PersonLastName": "Ortíz",
        "n_PersonGenderID": 1,
        "n_PersonNatioGeoID": 4370,
        "c_PersonNatio": "Paraguay",
        "c_PersonNatioShort": "PAR",
        "n_TeamNatioGeoID": 2201,
        "c_TeamNatio": "Nederland",
        "c_TeamNatioShort": "NED",
        "n_FunctionType": 4,
        "c_Function": "Middenvelder",
        "c_FunctionShort": "M",
        "n_FunctionCode": 4,
        "b_Captain": false,
        "n_ShirtNr": 6,
        "n_Position": 7,
        "n_SubPersonID": 954157,
        "c_SubPerson": "Robert Mühren",
        "c_SubPersonShort": "Mühren",
        "c_ActionMinute": "64'",
        "b_StartingLineUp": true,
        "b_RedCard": false,
        "c_LineUpInMinute": null,
        "c_LineUpOutMinute": "64'",
        "n_Client_PersonID": null
    },
    "PlayerLeague": [
        {
            "n_CompetitionID": 413,
            "n_CompetitionLevel": 1,
            "c_Competition": "Division de Honor",
            "c_CompetitionShort": null,
            "n_CompetitionNatioGeoID": 4370,
            "c_CompetitionNatio": "Paraguay",
            "c_CompetitionNatioShort": "PAR",
            "c_Season": "2008",
            "n_EditionID": 16258,
            "c_Edition": "2008 Apertura",
            "d_EditionStartDate": "/Date(1199142000000+0100)/",
            "d_EditionEndDate": "/Date(1214776800000+0200)/",
            "n_PersonNatioGeoID": 4370,
            "n_TeamID": 103121,
            "c_Team": "Cerro Porteño",
            "c_TeamShort": "CER",
            "n_TeamNatioGeoID": 4370,
            "c_TeamNatio": "Paraguay",
            "c_TeamNatioShort": "PAR",
            "n_FunctionType": 4,
            "c_Function": "Middenvelder",
            "c_FunctionShort": "M",
            "n_FunctionCode": 4,
            "n_DateSort": 20080101,
            "n_Matches": 2,
            "n_MatchesStart": null,
            "n_MatchesOut": null,
            "n_MatchesIn": null,
            "n_MinutesPlayed": null,
            "n_Goals": 0,
            "n_OwnGoals": null,
            "n_Assists": null,
            "n_CardsRedDirect": null,
            "n_CardsRed2Yellow": null,
            "n_CardsRed": null,
            "n_CardsYellow": null
        },
        {
            "n_CompetitionID": 2,
            "n_CompetitionLevel": 1,
            "c_Competition": "Eredivisie",
            "c_CompetitionShort": "Ere",
            "n_CompetitionNatioGeoID": 2201,
            "c_CompetitionNatio": "Nederland",
            "c_CompetitionNatioShort": "NED",
            "c_Season": "2009/2010",
            "n_EditionID": 17234,
            "c_Edition": "2009/2010",
            "d_EditionStartDate": "/Date(1246399200000+0200)/",
            "d_EditionEndDate": "/Date(1277848800000+0200)/",
            "n_PersonNatioGeoID": 4370,
            "n_TeamID": 61,
            "c_Team": "AZ",
            "c_TeamShort": "AZ",
            "n_TeamNatioGeoID": 2201,
            "c_TeamNatio": "Nederland",
            "c_TeamNatioShort": "NED",
            "n_FunctionType": 4,
            "c_Function": "Middenvelder",
            "c_FunctionShort": "M",
            "n_FunctionCode": 4,
            "n_DateSort": 20100128,
            "n_Matches": 6,
            "n_MatchesStart": 3,
            "n_MatchesOut": 2,
            "n_MatchesIn": 3,
            "n_MinutesPlayed": 199,
            "n_Goals": 0,
            "n_OwnGoals": 0,
            "n_Assists": 0,
            "n_CardsRedDirect": 0,
            "n_CardsRed2Yellow": 0,
            "n_CardsRed": 0,
            "n_CardsYellow": 0
        },
        {
            "n_CompetitionID": 2,
            "n_CompetitionLevel": 1,
            "c_Competition": "Eredivisie",
            "c_CompetitionShort": "Ere",
            "n_CompetitionNatioGeoID": 2201,
            "c_CompetitionNatio": "Nederland",
            "c_CompetitionNatioShort": "NED",
            "c_Season": "2010/2011",
            "n_EditionID": 18090,
            "c_Edition": "2010/2011",
            "d_EditionStartDate": "/Date(1277935200000+0200)/",
            "d_EditionEndDate": "/Date(1309384800000+0200)/",
            "n_PersonNatioGeoID": 4370,
            "n_TeamID": 61,
            "c_Team": "AZ",
            "c_TeamShort": "AZ",
            "n_TeamNatioGeoID": 2201,
            "c_TeamNatio": "Nederland",
            "c_TeamNatioShort": "NED",
            "n_FunctionType": 4,
            "c_Function": "Middenvelder",
            "c_FunctionShort": "M",
            "n_FunctionCode": 4,
            "n_DateSort": 20100128,
            "n_Matches": 13,
            "n_MatchesStart": 3,
            "n_MatchesOut": 1,
            "n_MatchesIn": 10,
            "n_MinutesPlayed": 526,
            "n_Goals": 1,
            "n_OwnGoals": 0,
            "n_Assists": 0,
            "n_CardsRedDirect": 0,
            "n_CardsRed2Yellow": 0,
            "n_CardsRed": 0,
            "n_CardsYellow": 1
        },
        {
            "n_CompetitionID": 2,
            "n_CompetitionLevel": 1,
            "c_Competition": "Eredivisie",
            "c_CompetitionShort": "Ere",
            "n_CompetitionNatioGeoID": 2201,
            "c_CompetitionNatio": "Nederland",
            "c_CompetitionNatioShort": "NED",
            "c_Season": "2011/2012",
            "n_EditionID": 18803,
            "c_Edition": "2011/2012",
            "d_EditionStartDate": "/Date(1309471200000+0200)/",
            "d_EditionEndDate": "/Date(1341007200000+0200)/",
            "n_PersonNatioGeoID": 4370,
            "n_TeamID": 61,
            "c_Team": "AZ",
            "c_TeamShort": "AZ",
            "n_TeamNatioGeoID": 2201,
            "c_TeamNatio": "Nederland",
            "c_TeamNatioShort": "NED",
            "n_FunctionType": 4,
            "c_Function": "Middenvelder",
            "c_FunctionShort": "M",
            "n_FunctionCode": 4,
            "n_DateSort": 20100128,
            "n_Matches": 4,
            "n_MatchesStart": 2,
            "n_MatchesOut": 2,
            "n_MatchesIn": 2,
            "n_MinutesPlayed": 158,
            "n_Goals": 0,
            "n_OwnGoals": 0,
            "n_Assists": 0,
            "n_CardsRedDirect": 0,
            "n_CardsRed2Yellow": 0,
            "n_CardsRed": 0,
            "n_CardsYellow": 0
        },
        {
            "n_CompetitionID": 2,
            "n_CompetitionLevel": 1,
            "c_Competition": "Eredivisie",
            "c_CompetitionShort": "Ere",
            "n_CompetitionNatioGeoID": 2201,
            "c_CompetitionNatio": "Nederland",
            "c_CompetitionNatioShort": "NED",
            "c_Season": "2012/2013",
            "n_EditionID": 19832,
            "c_Edition": "2012/2013",
            "d_EditionStartDate": "/Date(1341093600000+0200)/",
            "d_EditionEndDate": "/Date(1372543200000+0200)/",
            "n_PersonNatioGeoID": 4370,
            "n_TeamID": 61,
            "c_Team": "AZ",
            "c_TeamShort": "AZ",
            "n_TeamNatioGeoID": 2201,
            "c_TeamNatio": "Nederland",
            "c_TeamNatioShort": "NED",
            "n_FunctionType": 4,
            "c_Function": "Middenvelder",
            "c_FunctionShort": "M",
            "n_FunctionCode": 4,
            "n_DateSort": 20100128,
            "n_Matches": 4,
            "n_MatchesStart": 1,
            "n_MatchesOut": 0,
            "n_MatchesIn": 3,
            "n_MinutesPlayed": 146,
            "n_Goals": 0,
            "n_OwnGoals": 0,
            "n_Assists": 0,
            "n_CardsRedDirect": 0,
            "n_CardsRed2Yellow": 0,
            "n_CardsRed": 0,
            "n_CardsYellow": 1
        },
        {
            "n_CompetitionID": 2,
            "n_CompetitionLevel": 1,
            "c_Competition": "Eredivisie",
            "c_CompetitionShort": "Ere",
            "n_CompetitionNatioGeoID": 2201,
            "c_CompetitionNatio": "Nederland",
            "c_CompetitionNatioShort": "NED",
            "c_Season": "2013/2014",
            "n_EditionID": 20864,
            "c_Edition": "2013/2014",
            "d_EditionStartDate": "/Date(1372629600000+0200)/",
            "d_EditionEndDate": "/Date(1404079200000+0200)/",
            "n_PersonNatioGeoID": 4370,
            "n_TeamID": 61,
            "c_Team": "AZ",
            "c_TeamShort": "AZ",
            "n_TeamNatioGeoID": 2201,
            "c_TeamNatio": "Nederland",
            "c_TeamNatioShort": "NED",
            "n_FunctionType": 4,
            "c_Function": "Middenvelder",
            "c_FunctionShort": "M",
            "n_FunctionCode": 4,
            "n_DateSort": 20100128,
            "n_Matches": 27,
            "n_MatchesStart": 26,
            "n_MatchesOut": 11,
            "n_MatchesIn": 1,
            "n_MinutesPlayed": 2087,
            "n_Goals": 0,
            "n_OwnGoals": 0,
            "n_Assists": 1,
            "n_CardsRedDirect": 0,
            "n_CardsRed2Yellow": 0,
            "n_CardsRed": 0,
            "n_CardsYellow": 3
        },
        {
            "n_CompetitionID": 2,
            "n_CompetitionLevel": 1,
            "c_Competition": "Eredivisie",
            "c_CompetitionShort": "Ere",
            "n_CompetitionNatioGeoID": 2201,
            "c_CompetitionNatio": "Nederland",
            "c_CompetitionNatioShort": "NED",
            "c_Season": "2014/2015",
            "n_EditionID": 21399,
            "c_Edition": "2014/2015",
            "d_EditionStartDate": "/Date(1404165600000+0200)/",
            "d_EditionEndDate": "/Date(1435615200000+0200)/",
            "n_PersonNatioGeoID": 4370,
            "n_TeamID": 61,
            "c_Team": "AZ",
            "c_TeamShort": "AZ",
            "n_TeamNatioGeoID": 2201,
            "c_TeamNatio": "Nederland",
            "c_TeamNatioShort": "NED",
            "n_FunctionType": 4,
            "c_Function": "Middenvelder",
            "c_FunctionShort": "M",
            "n_FunctionCode": 4,
            "n_DateSort": 20100128,
            "n_Matches": 24,
            "n_MatchesStart": 24,
            "n_MatchesOut": 5,
            "n_MatchesIn": 0,
            "n_MinutesPlayed": 2004,
            "n_Goals": 0,
            "n_OwnGoals": 0,
            "n_Assists": 0,
            "n_CardsRedDirect": 0,
            "n_CardsRed2Yellow": 0,
            "n_CardsRed": 0,
            "n_CardsYellow": 2
        },
        {
            "n_CompetitionID": 2,
            "n_CompetitionLevel": 1,
            "c_Competition": "Eredivisie",
            "c_CompetitionShort": "Ere",
            "n_CompetitionNatioGeoID": 2201,
            "c_CompetitionNatio": "Nederland",
            "c_CompetitionNatioShort": "NED",
            "c_Season": "2015/2016",
            "n_EditionID": 21765,
            "c_Edition": "2015/2016",
            "d_EditionStartDate": "/Date(1435701600000+0200)/",
            "d_EditionEndDate": "/Date(1467237600000+0200)/",
            "n_PersonNatioGeoID": 4370,
            "n_TeamID": 61,
            "c_Team": "AZ",
            "c_TeamShort": "AZ",
            "n_TeamNatioGeoID": 2201,
            "c_TeamNatio": "Nederland",
            "c_TeamNatioShort": "NED",
            "n_FunctionType": 4,
            "c_Function": "Middenvelder",
            "c_FunctionShort": "M",
            "n_FunctionCode": 4,
            "n_DateSort": 20100128,
            "n_Matches": 18,
            "n_MatchesStart": 6,
            "n_MatchesOut": 4,
            "n_MatchesIn": 12,
            "n_MinutesPlayed": 680,
            "n_Goals": 0,
            "n_OwnGoals": 0,
            "n_Assists": 0,
            "n_CardsRedDirect": 0,
            "n_CardsRed2Yellow": 0,
            "n_CardsRed": 0,
            "n_CardsYellow": 1
        },
        {
            "n_CompetitionID": 208,
            "n_CompetitionLevel": 1,
            "c_Competition": "Liga BBVA Bancomer MX",
            "c_CompetitionShort": null,
            "n_CompetitionNatioGeoID": 2228,
            "c_CompetitionNatio": "Mexico",
            "c_CompetitionNatioShort": "MEX",
            "c_Season": "2016/2017",
            "n_EditionID": 22515,
            "c_Edition": "2016 Apertura",
            "d_EditionStartDate": "/Date(1467324000000+0200)/",
            "d_EditionEndDate": "/Date(1483138800000+0100)/",
            "n_PersonNatioGeoID": 4370,
            "n_TeamID": 103042,
            "c_Team": "Monterrey",
            "c_TeamShort": "MON",
            "n_TeamNatioGeoID": 2228,
            "c_TeamNatio": "Mexico",
            "c_TeamNatioShort": "MEX",
            "n_FunctionType": 4,
            "c_Function": "Middenvelder",
            "c_FunctionShort": "M",
            "n_FunctionCode": 4,
            "n_DateSort": 20160701,
            "n_Matches": 14,
            "n_MatchesStart": 14,
            "n_MatchesOut": 6,
            "n_MatchesIn": 0,
            "n_MinutesPlayed": 1180,
            "n_Goals": 1,
            "n_OwnGoals": 0,
            "n_Assists": null,
            "n_CardsRedDirect": 0,
            "n_CardsRed2Yellow": 0,
            "n_CardsRed": 0,
            "n_CardsYellow": 3
        },
        {
            "n_CompetitionID": 208,
            "n_CompetitionLevel": 1,
            "c_Competition": "Liga BBVA Bancomer MX",
            "c_CompetitionShort": null,
            "n_CompetitionNatioGeoID": 2228,
            "c_CompetitionNatio": "Mexico",
            "c_CompetitionNatioShort": "MEX",
            "c_Season": "2016/2017",
            "n_EditionID": 22738,
            "c_Edition": "2017 Clausura",
            "d_EditionStartDate": "/Date(1483225200000+0100)/",
            "d_EditionEndDate": "/Date(1498773600000+0200)/",
            "n_PersonNatioGeoID": 4370,
            "n_TeamID": 103042,
            "c_Team": "Monterrey",
            "c_TeamShort": "MON",
            "n_TeamNatioGeoID": 2228,
            "c_TeamNatio": "Mexico",
            "c_TeamNatioShort": "MEX",
            "n_FunctionType": 4,
            "c_Function": "Middenvelder",
            "c_FunctionShort": "M",
            "n_FunctionCode": 4,
            "n_DateSort": 20160701,
            "n_Matches": 14,
            "n_MatchesStart": 13,
            "n_MatchesOut": 6,
            "n_MatchesIn": 1,
            "n_MinutesPlayed": 1008,
            "n_Goals": 0,
            "n_OwnGoals": 0,
            "n_Assists": null,
            "n_CardsRedDirect": 0,
            "n_CardsRed2Yellow": 0,
            "n_CardsRed": 0,
            "n_CardsYellow": 3
        },
        {
            "n_CompetitionID": 208,
            "n_CompetitionLevel": 1,
            "c_Competition": "Liga BBVA Bancomer MX",
            "c_CompetitionShort": null,
            "n_CompetitionNatioGeoID": 2228,
            "c_CompetitionNatio": "Mexico",
            "c_CompetitionNatioShort": "MEX",
            "c_Season": "2017/2018",
            "n_EditionID": 22912,
            "c_Edition": "2017 Apertura",
            "d_EditionStartDate": "/Date(1498860000000+0200)/",
            "d_EditionEndDate": "/Date(1514674800000+0100)/",
            "n_PersonNatioGeoID": 4370,
            "n_TeamID": 103042,
            "c_Team": "Monterrey",
            "c_TeamShort": "MON",
            "n_TeamNatioGeoID": 2228,
            "c_TeamNatio": "Mexico",
            "c_TeamNatioShort": "MEX",
            "n_FunctionType": 4,
            "c_Function": "Middenvelder",
            "c_FunctionShort": "M",
            "n_FunctionCode": 4,
            "n_DateSort": 20160701,
            "n_Matches": 14,
            "n_MatchesStart": 14,
            "n_MatchesOut": 9,
            "n_MatchesIn": 0,
            "n_MinutesPlayed": 1084,
            "n_Goals": 1,
            "n_OwnGoals": 0,
            "n_Assists": null,
            "n_CardsRedDirect": 0,
            "n_CardsRed2Yellow": 0,
            "n_CardsRed": 0,
            "n_CardsYellow": 1
        },
        {
            "n_CompetitionID": 208,
            "n_CompetitionLevel": 1,
            "c_Competition": "Liga BBVA Bancomer MX",
            "c_CompetitionShort": null,
            "n_CompetitionNatioGeoID": 2228,
            "c_CompetitionNatio": "Mexico",
            "c_CompetitionNatioShort": "MEX",
            "c_Season": "2017/2018",
            "n_EditionID": 23336,
            "c_Edition": "2018 Clausura",
            "d_EditionStartDate": "/Date(1514761200000+0100)/",
            "d_EditionEndDate": "/Date(1530309600000+0200)/",
            "n_PersonNatioGeoID": 4370,
            "n_TeamID": 103042,
            "c_Team": "Monterrey",
            "c_TeamShort": "MON",
            "n_TeamNatioGeoID": 2228,
            "c_TeamNatio": "Mexico",
            "c_TeamNatioShort": "MEX",
            "n_FunctionType": 4,
            "c_Function": "Middenvelder",
            "c_FunctionShort": "M",
            "n_FunctionCode": 4,
            "n_DateSort": 20160701,
            "n_Matches": 17,
            "n_MatchesStart": 16,
            "n_MatchesOut": 5,
            "n_MatchesIn": 1,
            "n_MinutesPlayed": 1366,
            "n_Goals": 1,
            "n_OwnGoals": 0,
            "n_Assists": null,
            "n_CardsRedDirect": 0,
            "n_CardsRed2Yellow": 0,
            "n_CardsRed": 0,
            "n_CardsYellow": 1
        },
        {
            "n_CompetitionID": 208,
            "n_CompetitionLevel": 1,
            "c_Competition": "Liga BBVA Bancomer MX",
            "c_CompetitionShort": null,
            "n_CompetitionNatioGeoID": 2228,
            "c_CompetitionNatio": "Mexico",
            "c_CompetitionNatioShort": "MEX",
            "c_Season": "2018/2019",
            "n_EditionID": 23530,
            "c_Edition": "2018 Apertura",
            "d_EditionStartDate": "/Date(1530396000000+0200)/",
            "d_EditionEndDate": "/Date(1546210800000+0100)/",
            "n_PersonNatioGeoID": 4370,
            "n_TeamID": 103042,
            "c_Team": "Monterrey",
            "c_TeamShort": "MON",
            "n_TeamNatioGeoID": 2228,
            "c_TeamNatio": "Mexico",
            "c_TeamNatioShort": "MEX",
            "n_FunctionType": 4,
            "c_Function": "Middenvelder",
            "c_FunctionShort": "M",
            "n_FunctionCode": 4,
            "n_DateSort": 20160701,
            "n_Matches": 18,
            "n_MatchesStart": 16,
            "n_MatchesOut": 5,
            "n_MatchesIn": 2,
            "n_MinutesPlayed": 1330,
            "n_Goals": 1,
            "n_OwnGoals": 0,
            "n_Assists": null,
            "n_CardsRedDirect": 0,
            "n_CardsRed2Yellow": 0,
            "n_CardsRed": 0,
            "n_CardsYellow": 1
        },
        {
            "n_CompetitionID": 208,
            "n_CompetitionLevel": 1,
            "c_Competition": "Liga BBVA Bancomer MX",
            "c_CompetitionShort": null,
            "n_CompetitionNatioGeoID": 2228,
            "c_CompetitionNatio": "Mexico",
            "c_CompetitionNatioShort": "MEX",
            "c_Season": "2018/2019",
            "n_EditionID": 23927,
            "c_Edition": "2019 Clausura",
            "d_EditionStartDate": "/Date(1546297200000+0100)/",
            "d_EditionEndDate": "/Date(1561845600000+0200)/",
            "n_PersonNatioGeoID": 4370,
            "n_TeamID": 103042,
            "c_Team": "Monterrey",
            "c_TeamShort": "MON",
            "n_TeamNatioGeoID": 2228,
            "c_TeamNatio": "Mexico",
            "c_TeamNatioShort": "MEX",
            "n_FunctionType": 4,
            "c_Function": "Middenvelder",
            "c_FunctionShort": "M",
            "n_FunctionCode": 4,
            "n_DateSort": 20160701,
            "n_Matches": 16,
            "n_MatchesStart": 15,
            "n_MatchesOut": 3,
            "n_MatchesIn": 1,
            "n_MinutesPlayed": 1275,
            "n_Goals": 0,
            "n_OwnGoals": 0,
            "n_Assists": null,
            "n_CardsRedDirect": 0,
            "n_CardsRed2Yellow": 0,
            "n_CardsRed": 0,
            "n_CardsYellow": 1
        },
        {
            "n_CompetitionID": 208,
            "n_CompetitionLevel": 1,
            "c_Competition": "Liga BBVA MX",
            "c_CompetitionShort": null,
            "n_CompetitionNatioGeoID": 2228,
            "c_CompetitionNatio": "Mexico",
            "c_CompetitionNatioShort": "MEX",
            "c_Season": "2019/2020",
            "n_EditionID": 24640,
            "c_Edition": "2020 Clausura",
            "d_EditionStartDate": "/Date(1577833200000+0100)/",
            "d_EditionEndDate": "/Date(1593468000000+0200)/",
            "n_PersonNatioGeoID": 4370,
            "n_TeamID": 103042,
            "c_Team": "Monterrey",
            "c_TeamShort": "MON",
            "n_TeamNatioGeoID": 2228,
            "c_TeamNatio": "Mexico",
            "c_TeamNatioShort": "MEX",
            "n_FunctionType": 4,
            "c_Function": "Middenvelder",
            "c_FunctionShort": "M",
            "n_FunctionCode": 4,
            "n_DateSort": 20160701,
            "n_Matches": 9,
            "n_MatchesStart": 8,
            "n_MatchesOut": 1,
            "n_MatchesIn": 1,
            "n_MinutesPlayed": 735,
            "n_Goals": 0,
            "n_OwnGoals": 0,
            "n_Assists": null,
            "n_CardsRedDirect": 0,
            "n_CardsRed2Yellow": 0,
            "n_CardsRed": 0,
            "n_CardsYellow": 1
        }
    ],
    "PlayerCup": [
        {
            "n_CompetitionID": 4,
            "n_CompetitionLevel": 1,
            "c_Competition": "KNVB Beker",
            "c_CompetitionShort": "KNVB",
            "n_CompetitionNatioGeoID": 2201,
            "c_CompetitionNatio": "Nederland",
            "c_CompetitionNatioShort": "NED",
            "c_Season": "2010/2011",
            "n_EditionID": 18259,
            "c_Edition": "2010/2011",
            "d_EditionStartDate": "/Date(1277935200000+0200)/",
            "d_EditionEndDate": "/Date(1309384800000+0200)/",
            "n_PersonNatioGeoID": 4370,
            "n_TeamID": 61,
            "c_Team": "AZ",
            "c_TeamShort": "AZ",
            "n_TeamNatioGeoID": 2201,
            "c_TeamNatio": "Nederland",
            "c_TeamNatioShort": "NED",
            "n_FunctionType": 4,
            "c_Function": "Middenvelder",
            "c_FunctionShort": "M",
            "n_FunctionCode": 4,
            "n_DateSort": 20100128,
            "n_Matches": 1,
            "n_MatchesStart": 0,
            "n_MatchesOut": 0,
            "n_MatchesIn": 1,
            "n_MinutesPlayed": 15,
            "n_Goals": 0,
            "n_OwnGoals": 0,
            "n_Assists": null,
            "n_CardsRedDirect": 0,
            "n_CardsRed2Yellow": 0,
            "n_CardsRed": 0,
            "n_CardsYellow": 0
        },
        {
            "n_CompetitionID": 4,
            "n_CompetitionLevel": 1,
            "c_Competition": "KNVB Beker",
            "c_CompetitionShort": "KNVB",
            "n_CompetitionNatioGeoID": 2201,
            "c_CompetitionNatio": "Nederland",
            "c_CompetitionNatioShort": "NED",
            "c_Season": "2011/2012",
            "n_EditionID": 18834,
            "c_Edition": "2011/2012",
            "d_EditionStartDate": "/Date(1309471200000+0200)/",
            "d_EditionEndDate": "/Date(1341007200000+0200)/",
            "n_PersonNatioGeoID": 4370,
            "n_TeamID": 61,
            "c_Team": "AZ",
            "c_TeamShort": "AZ",
            "n_TeamNatioGeoID": 2201,
            "c_TeamNatio": "Nederland",
            "c_TeamNatioShort": "NED",
            "n_FunctionType": 4,
            "c_Function": "Middenvelder",
            "c_FunctionShort": "M",
            "n_FunctionCode": 4,
            "n_DateSort": 20100128,
            "n_Matches": 2,
            "n_MatchesStart": 0,
            "n_MatchesOut": 0,
            "n_MatchesIn": 2,
            "n_MinutesPlayed": 63,
            "n_Goals": 0,
            "n_OwnGoals": 0,
            "n_Assists": null,
            "n_CardsRedDirect": 0,
            "n_CardsRed2Yellow": 0,
            "n_CardsRed": 0,
            "n_CardsYellow": 0
        },
        {
            "n_CompetitionID": 4,
            "n_CompetitionLevel": 1,
            "c_Competition": "KNVB Beker",
            "c_CompetitionShort": "KNVB",
            "n_CompetitionNatioGeoID": 2201,
            "c_CompetitionNatio": "Nederland",
            "c_CompetitionNatioShort": "NED",
            "c_Season": "2012/2013",
            "n_EditionID": 20307,
            "c_Edition": "2012/2013",
            "d_EditionStartDate": "/Date(1341093600000+0200)/",
            "d_EditionEndDate": "/Date(1372543200000+0200)/",
            "n_PersonNatioGeoID": 4370,
            "n_TeamID": 61,
            "c_Team": "AZ",
            "c_TeamShort": "AZ",
            "n_TeamNatioGeoID": 2201,
            "c_TeamNatio": "Nederland",
            "c_TeamNatioShort": "NED",
            "n_FunctionType": 4,
            "c_Function": "Middenvelder",
            "c_FunctionShort": "M",
            "n_FunctionCode": 4,
            "n_DateSort": 20100128,
            "n_Matches": 0,
            "n_MatchesStart": 0,
            "n_MatchesOut": 0,
            "n_MatchesIn": 0,
            "n_MinutesPlayed": 0,
            "n_Goals": 0,
            "n_OwnGoals": 0,
            "n_Assists": null,
            "n_CardsRedDirect": 0,
            "n_CardsRed2Yellow": 0,
            "n_CardsRed": 0,
            "n_CardsYellow": 0
        },
        {
            "n_CompetitionID": 4,
            "n_CompetitionLevel": 1,
            "c_Competition": "KNVB Beker",
            "c_CompetitionShort": "KNVB",
            "n_CompetitionNatioGeoID": 2201,
            "c_CompetitionNatio": "Nederland",
            "c_CompetitionNatioShort": "NED",
            "c_Season": "2013/2014",
            "n_EditionID": 20835,
            "c_Edition": "2013/2014",
            "d_EditionStartDate": "/Date(1372629600000+0200)/",
            "d_EditionEndDate": "/Date(1404079200000+0200)/",
            "n_PersonNatioGeoID": 4370,
            "n_TeamID": 61,
            "c_Team": "AZ",
            "c_TeamShort": "AZ",
            "n_TeamNatioGeoID": 2201,
            "c_TeamNatio": "Nederland",
            "c_TeamNatioShort": "NED",
            "n_FunctionType": 4,
            "c_Function": "Middenvelder",
            "c_FunctionShort": "M",
            "n_FunctionCode": 4,
            "n_DateSort": 20100128,
            "n_Matches": 3,
            "n_MatchesStart": 3,
            "n_MatchesOut": 2,
            "n_MatchesIn": 0,
            "n_MinutesPlayed": 257,
            "n_Goals": 0,
            "n_OwnGoals": 0,
            "n_Assists": null,
            "n_CardsRedDirect": 0,
            "n_CardsRed2Yellow": 0,
            "n_CardsRed": 0,
            "n_CardsYellow": 0
        },
        {
            "n_CompetitionID": 3,
            "n_CompetitionLevel": 0,
            "c_Competition": "Johan Cruijff Schaal",
            "c_CompetitionShort": null,
            "n_CompetitionNatioGeoID": 2201,
            "c_CompetitionNatio": "Nederland",
            "c_CompetitionNatioShort": "NED",
            "c_Season": "2013/2014",
            "n_EditionID": 20855,
            "c_Edition": "2013",
            "d_EditionStartDate": "/Date(1372629600000+0200)/",
            "d_EditionEndDate": "/Date(1404079200000+0200)/",
            "n_PersonNatioGeoID": 4370,
            "n_TeamID": 61,
            "c_Team": "AZ",
            "c_TeamShort": "AZ",
            "n_TeamNatioGeoID": 2201,
            "c_TeamNatio": "Nederland",
            "c_TeamNatioShort": "NED",
            "n_FunctionType": 4,
            "c_Function": "Middenvelder",
            "c_FunctionShort": "M",
            "n_FunctionCode": 4,
            "n_DateSort": 20100128,
            "n_Matches": 0,
            "n_MatchesStart": 0,
            "n_MatchesOut": 0,
            "n_MatchesIn": 0,
            "n_MinutesPlayed": 0,
            "n_Goals": 0,
            "n_OwnGoals": 0,
            "n_Assists": null,
            "n_CardsRedDirect": 0,
            "n_CardsRed2Yellow": 0,
            "n_CardsRed": 0,
            "n_CardsYellow": 0
        },
        {
            "n_CompetitionID": 4,
            "n_CompetitionLevel": 1,
            "c_Competition": "KNVB Beker",
            "c_CompetitionShort": "KNVB",
            "n_CompetitionNatioGeoID": 2201,
            "c_CompetitionNatio": "Nederland",
            "c_CompetitionNatioShort": "NED",
            "c_Season": "2014/2015",
            "n_EditionID": 21400,
            "c_Edition": "2014/2015",
            "d_EditionStartDate": "/Date(1404165600000+0200)/",
            "d_EditionEndDate": "/Date(1435615200000+0200)/",
            "n_PersonNatioGeoID": 4370,
            "n_TeamID": 61,
            "c_Team": "AZ",
            "c_TeamShort": "AZ",
            "n_TeamNatioGeoID": 2201,
            "c_TeamNatio": "Nederland",
            "c_TeamNatioShort": "NED",
            "n_FunctionType": 4,
            "c_Function": "Middenvelder",
            "c_FunctionShort": "M",
            "n_FunctionCode": 4,
            "n_DateSort": 20100128,
            "n_Matches": 3,
            "n_MatchesStart": 3,
            "n_MatchesOut": 0,
            "n_MatchesIn": 0,
            "n_MinutesPlayed": 270,
            "n_Goals": 0,
            "n_OwnGoals": 0,
            "n_Assists": null,
            "n_CardsRedDirect": 0,
            "n_CardsRed2Yellow": 0,
            "n_CardsRed": 0,
            "n_CardsYellow": 1
        },
        {
            "n_CompetitionID": 4,
            "n_CompetitionLevel": 1,
            "c_Competition": "KNVB Beker",
            "c_CompetitionShort": "KNVB",
            "n_CompetitionNatioGeoID": 2201,
            "c_CompetitionNatio": "Nederland",
            "c_CompetitionNatioShort": "NED",
            "c_Season": "2015/2016",
            "n_EditionID": 21784,
            "c_Edition": "2015/2016",
            "d_EditionStartDate": "/Date(1435701600000+0200)/",
            "d_EditionEndDate": "/Date(1467237600000+0200)/",
            "n_PersonNatioGeoID": 4370,
            "n_TeamID": 61,
            "c_Team": "AZ",
            "c_TeamShort": "AZ",
            "n_TeamNatioGeoID": 2201,
            "c_TeamNatio": "Nederland",
            "c_TeamNatioShort": "NED",
            "n_FunctionType": 4,
            "c_Function": "Middenvelder",
            "c_FunctionShort": "M",
            "n_FunctionCode": 4,
            "n_DateSort": 20100128,
            "n_Matches": 2,
            "n_MatchesStart": 2,
            "n_MatchesOut": 0,
            "n_MatchesIn": 0,
            "n_MinutesPlayed": 180,
            "n_Goals": 0,
            "n_OwnGoals": 0,
            "n_Assists": null,
            "n_CardsRedDirect": 0,
            "n_CardsRed2Yellow": 0,
            "n_CardsRed": 0,
            "n_CardsYellow": 1
        }
    ],
    "PlayerInternationalclub": [
        {
            "n_CompetitionID": 43,
            "n_CompetitionLevel": 0,
            "c_Competition": "UEFA Europa League",
            "c_CompetitionShort": "Eur. League",
            "n_CompetitionNatioGeoID": 2101,
            "c_CompetitionNatio": "Europa",
            "c_CompetitionNatioShort": "EUR",
            "c_Season": "2010/2011",
            "n_EditionID": 18046,
            "c_Edition": "2010/2011",
            "d_EditionStartDate": "/Date(1277935200000+0200)/",
            "d_EditionEndDate": "/Date(1309212000000+0200)/",
            "n_PersonNatioGeoID": 4370,
            "n_TeamID": 61,
            "c_Team": "AZ",
            "c_TeamShort": "AZ",
            "n_TeamNatioGeoID": 2201,
            "c_TeamNatio": "Nederland",
            "c_TeamNatioShort": "NED",
            "n_FunctionType": 4,
            "c_Function": "Middenvelder",
            "c_FunctionShort": "M",
            "n_FunctionCode": 4,
            "n_DateSort": 20100128,
            "n_Matches": 5,
            "n_MatchesStart": 1,
            "n_MatchesOut": 0,
            "n_MatchesIn": 4,
            "n_MinutesPlayed": 147,
            "n_Goals": 0,
            "n_OwnGoals": 0,
            "n_Assists": null,
            "n_CardsRedDirect": 0,
            "n_CardsRed2Yellow": 0,
            "n_CardsRed": 0,
            "n_CardsYellow": 0
        },
        {
            "n_CompetitionID": 43,
            "n_CompetitionLevel": 0,
            "c_Competition": "UEFA Europa League",
            "c_CompetitionShort": "Eur. League",
            "n_CompetitionNatioGeoID": 2101,
            "c_CompetitionNatio": "Europa",
            "c_CompetitionNatioShort": "EUR",
            "c_Season": "2011/2012",
            "n_EditionID": 18773,
            "c_Edition": "2011/2012",
            "d_EditionStartDate": "/Date(1309298400000+0200)/",
            "d_EditionEndDate": "/Date(1341007200000+0200)/",
            "n_PersonNatioGeoID": 4370,
            "n_TeamID": 61,
            "c_Team": "AZ",
            "c_TeamShort": "AZ",
            "n_TeamNatioGeoID": 2201,
            "c_TeamNatio": "Nederland",
            "c_TeamNatioShort": "NED",
            "n_FunctionType": 4,
            "c_Function": "Middenvelder",
            "c_FunctionShort": "M",
            "n_FunctionCode": 4,
            "n_DateSort": 20100128,
            "n_Matches": 7,
            "n_MatchesStart": 0,
            "n_MatchesOut": 0,
            "n_MatchesIn": 7,
            "n_MinutesPlayed": 102,
            "n_Goals": 0,
            "n_OwnGoals": 0,
            "n_Assists": null,
            "n_CardsRedDirect": 0,
            "n_CardsRed2Yellow": 0,
            "n_CardsRed": 0,
            "n_CardsYellow": 0
        },
        {
            "n_CompetitionID": 43,
            "n_CompetitionLevel": 0,
            "c_Competition": "UEFA Europa League",
            "c_CompetitionShort": "Eur. League",
            "n_CompetitionNatioGeoID": 2101,
            "c_CompetitionNatio": "Europa",
            "c_CompetitionNatioShort": "EUR",
            "c_Season": "2012/2013",
            "n_EditionID": 19913,
            "c_Edition": "2012/2013",
            "d_EditionStartDate": "/Date(1341439200000+0200)/",
            "d_EditionEndDate": "/Date(1372543200000+0200)/",
            "n_PersonNatioGeoID": 4370,
            "n_TeamID": 61,
            "c_Team": "AZ",
            "c_TeamShort": "AZ",
            "n_TeamNatioGeoID": 2201,
            "c_TeamNatio": "Nederland",
            "c_TeamNatioShort": "NED",
            "n_FunctionType": 4,
            "c_Function": "Middenvelder",
            "c_FunctionShort": "M",
            "n_FunctionCode": 4,
            "n_DateSort": 20100128,
            "n_Matches": 0,
            "n_MatchesStart": 0,
            "n_MatchesOut": 0,
            "n_MatchesIn": 0,
            "n_MinutesPlayed": 0,
            "n_Goals": 0,
            "n_OwnGoals": 0,
            "n_Assists": null,
            "n_CardsRedDirect": 0,
            "n_CardsRed2Yellow": 0,
            "n_CardsRed": 0,
            "n_CardsYellow": 0
        },
        {
            "n_CompetitionID": 43,
            "n_CompetitionLevel": 0,
            "c_Competition": "UEFA Europa League",
            "c_CompetitionShort": "Eur. League",
            "n_CompetitionNatioGeoID": 2101,
            "c_CompetitionNatio": "Europa",
            "c_CompetitionNatioShort": "EUR",
            "c_Season": "2013/2014",
            "n_EditionID": 20626,
            "c_Edition": "2013/2014",
            "d_EditionStartDate": "/Date(1372629600000+0200)/",
            "d_EditionEndDate": "/Date(1404079200000+0200)/",
            "n_PersonNatioGeoID": 4370,
            "n_TeamID": 61,
            "c_Team": "AZ",
            "c_TeamShort": "AZ",
            "n_TeamNatioGeoID": 2201,
            "c_TeamNatio": "Nederland",
            "c_TeamNatioShort": "NED",
            "n_FunctionType": 4,
            "c_Function": "Middenvelder",
            "c_FunctionShort": "M",
            "n_FunctionCode": 4,
            "n_DateSort": 20100128,
            "n_Matches": 10,
            "n_MatchesStart": 10,
            "n_MatchesOut": 1,
            "n_MatchesIn": 0,
            "n_MinutesPlayed": 889,
            "n_Goals": 1,
            "n_OwnGoals": 0,
            "n_Assists": null,
            "n_CardsRedDirect": 0,
            "n_CardsRed2Yellow": 0,
            "n_CardsRed": 0,
            "n_CardsYellow": 1
        },
        {
            "n_CompetitionID": 43,
            "n_CompetitionLevel": 0,
            "c_Competition": "UEFA Europa League",
            "c_CompetitionShort": "Eur. League",
            "n_CompetitionNatioGeoID": 2101,
            "c_CompetitionNatio": "Europa",
            "c_CompetitionNatioShort": "EUR",
            "c_Season": "2015/2016",
            "n_EditionID": 21772,
            "c_Edition": "2015/2016",
            "d_EditionStartDate": "/Date(1435528800000+0200)/",
            "d_EditionEndDate": "/Date(1467237600000+0200)/",
            "n_PersonNatioGeoID": 4370,
            "n_TeamID": 61,
            "c_Team": "AZ",
            "c_TeamShort": "AZ",
            "n_TeamNatioGeoID": 2201,
            "c_TeamNatio": "Nederland",
            "c_TeamNatioShort": "NED",
            "n_FunctionType": 4,
            "c_Function": "Middenvelder",
            "c_FunctionShort": "M",
            "n_FunctionCode": 4,
            "n_DateSort": 20100128,
            "n_Matches": 6,
            "n_MatchesStart": 5,
            "n_MatchesOut": 2,
            "n_MatchesIn": 1,
            "n_MinutesPlayed": 462,
            "n_Goals": 0,
            "n_OwnGoals": 0,
            "n_Assists": null,
            "n_CardsRedDirect": 0,
            "n_CardsRed2Yellow": 0,
            "n_CardsRed": 0,
            "n_CardsYellow": 0
        },
        {
            "n_CompetitionID": 284,
            "n_CompetitionLevel": 0,
            "c_Competition": "FIFA Club World Cup",
            "c_CompetitionShort": null,
            "n_CompetitionNatioGeoID": 0,
            "c_CompetitionNatio": null,
            "c_CompetitionNatioShort": null,
            "c_Season": "2019",
            "n_EditionID": 24557,
            "c_Edition": "2019",
            "d_EditionStartDate": "/Date(1576018800000+0100)/",
            "d_EditionEndDate": "/Date(1576882800000+0100)/",
            "n_PersonNatioGeoID": 4370,
            "n_TeamID": 103042,
            "c_Team": "Monterrey",
            "c_TeamShort": "MON",
            "n_TeamNatioGeoID": 2228,
            "c_TeamNatio": "Mexico",
            "c_TeamNatioShort": "MEX",
            "n_FunctionType": 4,
            "c_Function": "Middenvelder",
            "c_FunctionShort": "M",
            "n_FunctionCode": 4,
            "n_DateSort": 20160701,
            "n_Matches": 1,
            "n_MatchesStart": 1,
            "n_MatchesOut": 0,
            "n_MatchesIn": 0,
            "n_MinutesPlayed": 90,
            "n_Goals": 0,
            "n_OwnGoals": 0,
            "n_Assists": null,
            "n_CardsRedDirect": 0,
            "n_CardsRed2Yellow": 0,
            "n_CardsRed": 0,
            "n_CardsYellow": 0
        }
    ],
    "PlayerInternational": [
        {
            "n_CompetitionID": 11,
            "n_CompetitionLevel": 0,
            "c_Competition": "Vriendschappelijk",
            "c_CompetitionShort": "Vriendsch.",
            "n_CompetitionNatioGeoID": 0,
            "c_CompetitionNatio": null,
            "c_CompetitionNatioShort": null,
            "c_Season": "2010",
            "n_EditionID": 17573,
            "c_Edition": "2010",
            "d_EditionStartDate": "/Date(1262300400000+0100)/",
            "d_EditionEndDate": "/Date(1293750000000+0100)/",
            "n_PersonNatioGeoID": 4370,
            "n_TeamID": 3028,
            "c_Team": "Paraguay",
            "c_TeamShort": "PAR",
            "n_TeamNatioGeoID": 4370,
            "c_TeamNatio": "Paraguay",
            "c_TeamNatioShort": "PAR",
            "n_FunctionType": 4,
            "c_Function": "Middenvelder",
            "c_FunctionShort": "M",
            "n_FunctionCode": 4,
            "n_DateSort": 20100903,
            "n_Matches": 1,
            "n_MatchesStart": 0,
            "n_MatchesOut": 0,
            "n_MatchesIn": 1,
            "n_MinutesPlayed": 11,
            "n_Goals": 0,
            "n_OwnGoals": 0,
            "n_Assists": null,
            "n_CardsRedDirect": 0,
            "n_CardsRed2Yellow": 0,
            "n_CardsRed": 0,
            "n_CardsYellow": 0
        },
        {
            "n_CompetitionID": 11,
            "n_CompetitionLevel": 0,
            "c_Competition": "Vriendschappelijk",
            "c_CompetitionShort": "Vriendsch.",
            "n_CompetitionNatioGeoID": 0,
            "c_CompetitionNatio": null,
            "c_CompetitionNatioShort": null,
            "c_Season": "2011",
            "n_EditionID": 18461,
            "c_Edition": "2011",
            "d_EditionStartDate": "/Date(1293836400000+0100)/",
            "d_EditionEndDate": "/Date(1325286000000+0100)/",
            "n_PersonNatioGeoID": 4370,
            "n_TeamID": 3028,
            "c_Team": "Paraguay",
            "c_TeamShort": "PAR",
            "n_TeamNatioGeoID": 4370,
            "c_TeamNatio": "Paraguay",
            "c_TeamNatioShort": "PAR",
            "n_FunctionType": 4,
            "c_Function": "Middenvelder",
            "c_FunctionShort": "M",
            "n_FunctionCode": 4,
            "n_DateSort": 20100903,
            "n_Matches": 0,
            "n_MatchesStart": 0,
            "n_MatchesOut": 0,
            "n_MatchesIn": 0,
            "n_MinutesPlayed": 0,
            "n_Goals": 0,
            "n_OwnGoals": 0,
            "n_Assists": null,
            "n_CardsRedDirect": 0,
            "n_CardsRed2Yellow": 0,
            "n_CardsRed": 0,
            "n_CardsYellow": 0
        },
        {
            "n_CompetitionID": 11,
            "n_CompetitionLevel": 0,
            "c_Competition": "Vriendschappelijk",
            "c_CompetitionShort": "Vriendsch.",
            "n_CompetitionNatioGeoID": 0,
            "c_CompetitionNatio": null,
            "c_CompetitionNatioShort": null,
            "c_Season": "2014",
            "n_EditionID": 20981,
            "c_Edition": "2014",
            "d_EditionStartDate": "/Date(1388530800000+0100)/",
            "d_EditionEndDate": "/Date(1419980400000+0100)/",
            "n_PersonNatioGeoID": 4370,
            "n_TeamID": 3028,
            "c_Team": "Paraguay",
            "c_TeamShort": "PAR",
            "n_TeamNatioGeoID": 4370,
            "c_TeamNatio": "Paraguay",
            "c_TeamNatioShort": "PAR",
            "n_FunctionType": 4,
            "c_Function": "Middenvelder",
            "c_FunctionShort": "M",
            "n_FunctionCode": 4,
            "n_DateSort": 0,
            "n_Matches": 1,
            "n_MatchesStart": 1,
            "n_MatchesOut": 1,
            "n_MatchesIn": 0,
            "n_MinutesPlayed": 68,
            "n_Goals": 0,
            "n_OwnGoals": 0,
            "n_Assists": null,
            "n_CardsRedDirect": 0,
            "n_CardsRed2Yellow": 0,
            "n_CardsRed": 0,
            "n_CardsYellow": 0
        },
        {
            "n_CompetitionID": 11,
            "n_CompetitionLevel": 0,
            "c_Competition": "Vriendschappelijk",
            "c_CompetitionShort": "Vriendsch.",
            "n_CompetitionNatioGeoID": 0,
            "c_CompetitionNatio": null,
            "c_CompetitionNatioShort": null,
            "c_Season": "2015",
            "n_EditionID": 21520,
            "c_Edition": "2015",
            "d_EditionStartDate": "/Date(1420066800000+0100)/",
            "d_EditionEndDate": "/Date(1451516400000+0100)/",
            "n_PersonNatioGeoID": 4370,
            "n_TeamID": 3028,
            "c_Team": "Paraguay",
            "c_TeamShort": "PAR",
            "n_TeamNatioGeoID": 4370,
            "c_TeamNatio": "Paraguay",
            "c_TeamNatioShort": "PAR",
            "n_FunctionType": 4,
            "c_Function": "Middenvelder",
            "c_FunctionShort": "M",
            "n_FunctionCode": 4,
            "n_DateSort": 20141009,
            "n_Matches": 0,
            "n_MatchesStart": 0,
            "n_MatchesOut": 0,
            "n_MatchesIn": 0,
            "n_MinutesPlayed": 0,
            "n_Goals": 0,
            "n_OwnGoals": 0,
            "n_Assists": null,
            "n_CardsRedDirect": 0,
            "n_CardsRed2Yellow": 0,
            "n_CardsRed": 0,
            "n_CardsYellow": 0
        },
        {
            "n_CompetitionID": 312,
            "n_CompetitionLevel": 0,
            "c_Competition": "Wereldkampioenschap Kwalificatie CONMEBOL",
            "c_CompetitionShort": "WK Kwal. CONMEB",
            "n_CompetitionNatioGeoID": 2106,
            "c_CompetitionNatio": "Zuid-Amerika",
            "c_CompetitionNatioShort": "SA",
            "c_Season": "2018",
            "n_EditionID": 22026,
            "c_Edition": "2018",
            "d_EditionStartDate": "/Date(1443909600000+0200)/",
            "d_EditionEndDate": "/Date(1509836400000+0100)/",
            "n_PersonNatioGeoID": 4370,
            "n_TeamID": 3028,
            "c_Team": "Paraguay",
            "c_TeamShort": "PAR",
            "n_TeamNatioGeoID": 4370,
            "c_TeamNatio": "Paraguay",
            "c_TeamNatioShort": "PAR",
            "n_FunctionType": 4,
            "c_Function": "Middenvelder",
            "c_FunctionShort": "M",
            "n_FunctionCode": 4,
            "n_DateSort": 20141009,
            "n_Matches": 3,
            "n_MatchesStart": 2,
            "n_MatchesOut": 1,
            "n_MatchesIn": 1,
            "n_MinutesPlayed": 173,
            "n_Goals": 0,
            "n_OwnGoals": 0,
            "n_Assists": null,
            "n_CardsRedDirect": 0,
            "n_CardsRed2Yellow": 0,
            "n_CardsRed": 0,
            "n_CardsYellow": 0
        },
        {
            "n_CompetitionID": 11,
            "n_CompetitionLevel": 0,
            "c_Competition": "Vriendschappelijk",
            "c_CompetitionShort": "Vriendsch.",
            "n_CompetitionNatioGeoID": 0,
            "c_CompetitionNatio": null,
            "c_CompetitionNatioShort": null,
            "c_Season": "2016",
            "n_EditionID": 22112,
            "c_Edition": "2016",
            "d_EditionStartDate": "/Date(1451602800000+0100)/",
            "d_EditionEndDate": "/Date(1483138800000+0100)/",
            "n_PersonNatioGeoID": 4370,
            "n_TeamID": 3028,
            "c_Team": "Paraguay",
            "c_TeamShort": "PAR",
            "n_TeamNatioGeoID": 4370,
            "c_TeamNatio": "Paraguay",
            "c_TeamNatioShort": "PAR",
            "n_FunctionType": 4,
            "c_Function": "Middenvelder",
            "c_FunctionShort": "M",
            "n_FunctionCode": 4,
            "n_DateSort": 20141009,
            "n_Matches": 1,
            "n_MatchesStart": 1,
            "n_MatchesOut": 0,
            "n_MatchesIn": 0,
            "n_MinutesPlayed": 90,
            "n_Goals": 0,
            "n_OwnGoals": 0,
            "n_Assists": null,
            "n_CardsRedDirect": 0,
            "n_CardsRed2Yellow": 0,
            "n_CardsRed": 0,
            "n_CardsYellow": 1
        },
        {
            "n_CompetitionID": 102,
            "n_CompetitionLevel": 0,
            "c_Competition": "Copa América",
            "c_CompetitionShort": null,
            "n_CompetitionNatioGeoID": 2106,
            "c_CompetitionNatio": "Zuid-Amerika",
            "c_CompetitionNatioShort": "SA",
            "c_Season": "2016",
            "n_EditionID": 22130,
            "c_Edition": "2016",
            "d_EditionStartDate": "/Date(1464818400000+0200)/",
            "d_EditionEndDate": "/Date(1466978400000+0200)/",
            "n_PersonNatioGeoID": 4370,
            "n_TeamID": 3028,
            "c_Team": "Paraguay",
            "c_TeamShort": "PAR",
            "n_TeamNatioGeoID": 4370,
            "c_TeamNatio": "Paraguay",
            "c_TeamNatioShort": "PAR",
            "n_FunctionType": 4,
            "c_Function": "Middenvelder",
            "c_FunctionShort": "M",
            "n_FunctionCode": 4,
            "n_DateSort": 20141009,
            "n_Matches": 3,
            "n_MatchesStart": 3,
            "n_MatchesOut": 1,
            "n_MatchesIn": 0,
            "n_MinutesPlayed": 235,
            "n_Goals": 0,
            "n_OwnGoals": 0,
            "n_Assists": null,
            "n_CardsRedDirect": 0,
            "n_CardsRed2Yellow": 0,
            "n_CardsRed": 0,
            "n_CardsYellow": 1
        },
        {
            "n_CompetitionID": 11,
            "n_CompetitionLevel": 0,
            "c_Competition": "Vriendschappelijk",
            "c_CompetitionShort": "Vriendsch.",
            "n_CompetitionNatioGeoID": 0,
            "c_CompetitionNatio": null,
            "c_CompetitionNatioShort": null,
            "c_Season": "2017",
            "n_EditionID": 22658,
            "c_Edition": "2017",
            "d_EditionStartDate": "/Date(1483225200000+0100)/",
            "d_EditionEndDate": "/Date(1514674800000+0100)/",
            "n_PersonNatioGeoID": 4370,
            "n_TeamID": 3028,
            "c_Team": "Paraguay",
            "c_TeamShort": "PAR",
            "n_TeamNatioGeoID": 4370,
            "c_TeamNatio": "Paraguay",
            "c_TeamNatioShort": "PAR",
            "n_FunctionType": 4,
            "c_Function": "Middenvelder",
            "c_FunctionShort": "M",
            "n_FunctionCode": 4,
            "n_DateSort": 20141009,
            "n_Matches": 0,
            "n_MatchesStart": 0,
            "n_MatchesOut": 0,
            "n_MatchesIn": 0,
            "n_MinutesPlayed": 0,
            "n_Goals": 0,
            "n_OwnGoals": 0,
            "n_Assists": null,
            "n_CardsRedDirect": 0,
            "n_CardsRed2Yellow": 0,
            "n_CardsRed": 0,
            "n_CardsYellow": 0
        },
        {
            "n_CompetitionID": 11,
            "n_CompetitionLevel": 0,
            "c_Competition": "Vriendschappelijk",
            "c_CompetitionShort": "Vriendsch.",
            "n_CompetitionNatioGeoID": 0,
            "c_CompetitionNatio": null,
            "c_CompetitionNatioShort": null,
            "c_Season": "2018",
            "n_EditionID": 23258,
            "c_Edition": "2018",
            "d_EditionStartDate": "/Date(1514761200000+0100)/",
            "d_EditionEndDate": "/Date(1546297140000+0100)/",
            "n_PersonNatioGeoID": 4370,
            "n_TeamID": 3028,
            "c_Team": "Paraguay",
            "c_TeamShort": "PAR",
            "n_TeamNatioGeoID": 4370,
            "c_TeamNatio": "Paraguay",
            "c_TeamNatioShort": "PAR",
            "n_FunctionType": 4,
            "c_Function": "Middenvelder",
            "c_FunctionShort": "M",
            "n_FunctionCode": 4,
            "n_DateSort": 20141009,
            "n_Matches": 0,
            "n_MatchesStart": 0,
            "n_MatchesOut": 0,
            "n_MatchesIn": 0,
            "n_MinutesPlayed": 0,
            "n_Goals": 0,
            "n_OwnGoals": 0,
            "n_Assists": null,
            "n_CardsRedDirect": 0,
            "n_CardsRed2Yellow": 0,
            "n_CardsRed": 0,
            "n_CardsYellow": 0
        },
        {
            "n_CompetitionID": 11,
            "n_CompetitionLevel": 0,
            "c_Competition": "Vriendschappelijk",
            "c_CompetitionShort": "Vriendsch.",
            "n_CompetitionNatioGeoID": 0,
            "c_CompetitionNatio": null,
            "c_CompetitionNatioShort": null,
            "c_Season": "2019",
            "n_EditionID": 23923,
            "c_Edition": "2019",
            "d_EditionStartDate": "/Date(1546297200000+0100)/",
            "d_EditionEndDate": "/Date(1577746800000+0100)/",
            "n_PersonNatioGeoID": 4370,
            "n_TeamID": 3028,
            "c_Team": "Paraguay",
            "c_TeamShort": "PAR",
            "n_TeamNatioGeoID": 4370,
            "c_TeamNatio": "Paraguay",
            "c_TeamNatioShort": "PAR",
            "n_FunctionType": 4,
            "c_Function": "Middenvelder",
            "c_FunctionShort": "M",
            "n_FunctionCode": 4,
            "n_DateSort": 20190101,
            "n_Matches": 1,
            "n_MatchesStart": 0,
            "n_MatchesOut": 0,
            "n_MatchesIn": 1,
            "n_MinutesPlayed": 23,
            "n_Goals": 0,
            "n_OwnGoals": 0,
            "n_Assists": null,
            "n_CardsRedDirect": 0,
            "n_CardsRed2Yellow": 0,
            "n_CardsRed": 0,
            "n_CardsYellow": 0
        },
        {
            "n_CompetitionID": 102,
            "n_CompetitionLevel": 0,
            "c_Competition": "Copa América",
            "c_CompetitionShort": null,
            "n_CompetitionNatioGeoID": 2106,
            "c_CompetitionNatio": "Zuid-Amerika",
            "c_CompetitionNatioShort": "SA",
            "c_Season": "2019",
            "n_EditionID": 23887,
            "c_Edition": "2019",
            "d_EditionStartDate": "/Date(1560463200000+0200)/",
            "d_EditionEndDate": "/Date(1562536800000+0200)/",
            "n_PersonNatioGeoID": 4370,
            "n_TeamID": 3028,
            "c_Team": "Paraguay",
            "c_TeamShort": "PAR",
            "n_TeamNatioGeoID": 4370,
            "c_TeamNatio": "Paraguay",
            "c_TeamNatioShort": "PAR",
            "n_FunctionType": 4,
            "c_Function": "Middenvelder",
            "c_FunctionShort": "M",
            "n_FunctionCode": 4,
            "n_DateSort": 20190101,
            "n_Matches": 3,
            "n_MatchesStart": 2,
            "n_MatchesOut": 0,
            "n_MatchesIn": 1,
            "n_MinutesPlayed": 185,
            "n_Goals": 0,
            "n_OwnGoals": 0,
            "n_Assists": null,
            "n_CardsRedDirect": 0,
            "n_CardsRed2Yellow": 0,
            "n_CardsRed": 0,
            "n_CardsYellow": 0
        }
    ]
}