{
    "PlayerInfo": [
        {
            "n_PersonID": 1495786,
            "c_FirstName": "Alessandro",
            "c_LastName": "Tripaldelli",
            "c_OfficialName": "Alessandro Tripaldelli",
            "c_OfficialNameSort": "Alessandro Tripaldelli",
            "c_PublicName": "Alessandro Tripaldelli",
            "c_PublicNameSort": "Tripaldelli, Alessandro",
            "c_Nickname": null,
            "n_GenderID": 1,
            "c_Gender": "Mannen",
            "c_GenderShort": "M",
            "n_NatioGeoID": 2210,
            "c_Natio": "Italië",
            "c_NatioShort": "ITA",
            "n_SecondNatioGeoID": 0,
            "c_SecondNatio": null,
            "c_SecondNatioShort": null,
            "d_BirthDate": "/Date(918514800000+0100)/",
            "n_BirthYear": null,
            "d_DeathDate": null,
            "n_DeathYear": null,
            "n_Height": 1820,
            "n_Weight": 76000,
            "n_BirthCityGeoID": 4705,
            "c_BirthCity": "Napels",
            "n_BirthCountryGeoID": 2210,
            "c_BirthCountry": "Italië",
            "c_BirthCountryShort": "ITA",
            "n_ResidenceCityGeoID": 0,
            "c_ResidenceCity": null,
            "n_ResidenceCountryGeoID": 0,
            "c_ResidenceCountry": null,
            "c_ResidenceCountryShort": null,
            "n_ClubTeamID": 112230,
            "c_ClubTeam": "Sassuolo",
            "n_ClubTeamNatioGeoID": 2210,
            "c_ClubTeamNatio": "Italië",
            "c_ClubTeamNatioShort": "ITA",
            "n_ClubTeamFunctionType": 2,
            "c_ClubTeamFunction": "Verdediger",
            "c_ClubTeamFunctionShort": "V",
            "n_ClubTeamFunctionCode": 2,
            "n_NatTeamID": 0,
            "c_NatTeam": null,
            "n_NatTeamFunctionType": 0,
            "c_NatTeamFunction": null,
            "c_NatTeamFunctionShort": null,
            "n_NatTeamFunctionCode": 0
        }
    ],
    "PlayerLeague": [
        {
            "n_CompetitionID": 2,
            "n_CompetitionLevel": 1,
            "c_Competition": "Eredivisie",
            "c_CompetitionShort": "Ere",
            "n_CompetitionNatioGeoID": 2201,
            "c_CompetitionNatio": "Nederland",
            "c_CompetitionNatioShort": "NED",
            "c_Season": "2018/2019",
            "n_EditionID": 23521,
            "c_Edition": "2018/2019",
            "d_EditionStartDate": "/Date(1530396000000+0200)/",
            "d_EditionEndDate": "/Date(1561845600000+0200)/",
            "n_PersonNatioGeoID": 2210,
            "n_TeamID": 73,
            "c_Team": "PEC Zwolle",
            "c_TeamShort": "ZWO",
            "n_TeamNatioGeoID": 2201,
            "c_TeamNatio": "Nederland",
            "c_TeamNatioShort": "NED",
            "n_FunctionType": 2,
            "c_Function": "Verdediger",
            "c_FunctionShort": "V",
            "n_FunctionCode": 2,
            "n_DateSort": 20180831,
            "n_Matches": 2,
            "n_MatchesStart": 1,
            "n_MatchesOut": 1,
            "n_MatchesIn": 1,
            "n_MinutesPlayed": 121,
            "n_Goals": 0,
            "n_OwnGoals": 0,
            "n_Assists": 0,
            "n_CardsRedDirect": 0,
            "n_CardsRed2Yellow": 0,
            "n_CardsRed": 0,
            "n_CardsYellow": 0
        },
        {
            "n_CompetitionID": 129,
            "n_CompetitionLevel": 2,
            "c_Competition": "Serie BKT",
            "c_CompetitionShort": null,
            "n_CompetitionNatioGeoID": 2210,
            "c_CompetitionNatio": "Italië",
            "c_CompetitionNatioShort": "ITA",
            "c_Season": "2018/2019",
            "n_EditionID": 23568,
            "c_Edition": "2018/2019",
            "d_EditionStartDate": "/Date(1530396000000+0200)/",
            "d_EditionEndDate": "/Date(1561845600000+0200)/",
            "n_PersonNatioGeoID": 2210,
            "n_TeamID": 105959,
            "c_Team": "Crotone",
            "c_TeamShort": "CRO",
            "n_TeamNatioGeoID": 2210,
            "c_TeamNatio": "Italië",
            "c_TeamNatioShort": "ITA",
            "n_FunctionType": 2,
            "c_Function": "Verdediger",
            "c_FunctionShort": "V",
            "n_FunctionCode": 2,
            "n_DateSort": 20190110,
            "n_Matches": 3,
            "n_MatchesStart": 2,
            "n_MatchesOut": 2,
            "n_MatchesIn": 1,
            "n_MinutesPlayed": 148,
            "n_Goals": 0,
            "n_OwnGoals": 0,
            "n_Assists": null,
            "n_CardsRedDirect": 0,
            "n_CardsRed2Yellow": 0,
            "n_CardsRed": 0,
            "n_CardsYellow": 0
        },
        {
            "n_CompetitionID": 53,
            "n_CompetitionLevel": 1,
            "c_Competition": "Serie A TIM",
            "c_CompetitionShort": null,
            "n_CompetitionNatioGeoID": 2210,
            "c_CompetitionNatio": "Italië",
            "c_CompetitionNatioShort": "ITA",
            "c_Season": "2019/2020",
            "n_EditionID": 24216,
            "c_Edition": "2019/2020",
            "d_EditionStartDate": "/Date(1561932000000+0200)/",
            "d_EditionEndDate": "/Date(1593468000000+0200)/",
            "n_PersonNatioGeoID": 2210,
            "n_TeamID": 112230,
            "c_Team": "Sassuolo",
            "c_TeamShort": "SAS",
            "n_TeamNatioGeoID": 2210,
            "c_TeamNatio": "Italië",
            "c_TeamNatioShort": "ITA",
            "n_FunctionType": 2,
            "c_Function": "Verdediger",
            "c_FunctionShort": "V",
            "n_FunctionCode": 2,
            "n_DateSort": 20190701,
            "n_Matches": 2,
            "n_MatchesStart": 1,
            "n_MatchesOut": 0,
            "n_MatchesIn": 1,
            "n_MinutesPlayed": 135,
            "n_Goals": 0,
            "n_OwnGoals": 0,
            "n_Assists": null,
            "n_CardsRedDirect": 0,
            "n_CardsRed2Yellow": 0,
            "n_CardsRed": 0,
            "n_CardsYellow": 0
        }
    ],
    "PlayerCup": [
        {
            "n_CompetitionID": 4,
            "n_CompetitionLevel": 1,
            "c_Competition": "TOTO KNVB Beker",
            "c_CompetitionShort": "KNVB",
            "n_CompetitionNatioGeoID": 2201,
            "c_CompetitionNatio": "Nederland",
            "c_CompetitionNatioShort": "NED",
            "c_Season": "2018/2019",
            "n_EditionID": 23543,
            "c_Edition": "2018/2019",
            "d_EditionStartDate": "/Date(1530396000000+0200)/",
            "d_EditionEndDate": "/Date(1561845600000+0200)/",
            "n_PersonNatioGeoID": 2210,
            "n_TeamID": 73,
            "c_Team": "PEC Zwolle",
            "c_TeamShort": "ZWO",
            "n_TeamNatioGeoID": 2201,
            "c_TeamNatio": "Nederland",
            "c_TeamNatioShort": "NED",
            "n_FunctionType": 2,
            "c_Function": "Verdediger",
            "c_FunctionShort": "V",
            "n_FunctionCode": 2,
            "n_DateSort": 20180831,
            "n_Matches": 0,
            "n_MatchesStart": 0,
            "n_MatchesOut": 0,
            "n_MatchesIn": 0,
            "n_MinutesPlayed": 0,
            "n_Goals": 0,
            "n_OwnGoals": 0,
            "n_Assists": null,
            "n_CardsRedDirect": 0,
            "n_CardsRed2Yellow": 0,
            "n_CardsRed": 0,
            "n_CardsYellow": 0
        },
        {
            "n_CompetitionID": 60,
            "n_CompetitionLevel": 1,
            "c_Competition": "Coppa Italia",
            "c_CompetitionShort": null,
            "n_CompetitionNatioGeoID": 2210,
            "c_CompetitionNatio": "Italië",
            "c_CompetitionNatioShort": "ITA",
            "c_Season": "2019/2020",
            "n_EditionID": 24222,
            "c_Edition": "2019/2020",
            "d_EditionStartDate": "/Date(1561932000000+0200)/",
            "d_EditionEndDate": "/Date(1593468000000+0200)/",
            "n_PersonNatioGeoID": 2210,
            "n_TeamID": 112230,
            "c_Team": "Sassuolo",
            "c_TeamShort": "SAS",
            "n_TeamNatioGeoID": 2210,
            "c_TeamNatio": "Italië",
            "c_TeamNatioShort": "ITA",
            "n_FunctionType": 2,
            "c_Function": "Verdediger",
            "c_FunctionShort": "V",
            "n_FunctionCode": 2,
            "n_DateSort": 20190701,
            "n_Matches": 1,
            "n_MatchesStart": 1,
            "n_MatchesOut": 1,
            "n_MatchesIn": 0,
            "n_MinutesPlayed": 58,
            "n_Goals": 0,
            "n_OwnGoals": 0,
            "n_Assists": null,
            "n_CardsRedDirect": 0,
            "n_CardsRed2Yellow": 0,
            "n_CardsRed": 0,
            "n_CardsYellow": 0
        }
    ],
    "PlayerInternationalclub": [],
    "PlayerInternational": []
}