{
    "PlayerInfo": [
        {
            "n_PersonID": 870535,
            "c_FirstName": "Aras",
            "c_LastName": "Özbiliz",
            "c_OfficialName": "Aras Özbiliz",
            "c_OfficialNameSort": "Aras Özbiliz",
            "c_PublicName": "Aras Özbiliz",
            "c_PublicNameSort": "Özbiliz, Aras",
            "c_Nickname": null,
            "n_GenderID": 1,
            "c_Gender": "Mannen",
            "c_GenderShort": "M",
            "n_NatioGeoID": 4317,
            "c_Natio": "Armenië",
            "c_NatioShort": "ARM",
            "n_SecondNatioGeoID": 0,
            "c_SecondNatio": null,
            "c_SecondNatioShort": null,
            "d_BirthDate": "/Date(636937200000+0100)/",
            "n_BirthYear": null,
            "d_DeathDate": null,
            "n_DeathYear": null,
            "n_Height": 1750,
            "n_Weight": 72000,
            "n_BirthCityGeoID": 38803,
            "c_BirthCity": "Bakirkoy",
            "n_BirthCountryGeoID": 2786,
            "c_BirthCountry": "Turkije",
            "c_BirthCountryShort": "TUR",
            "n_ResidenceCityGeoID": 0,
            "c_ResidenceCity": null,
            "n_ResidenceCountryGeoID": 0,
            "c_ResidenceCountry": null,
            "c_ResidenceCountryShort": null,
            "n_ClubTeamID": 5112,
            "c_ClubTeam": "FC Pyunik",
            "n_ClubTeamNatioGeoID": 4317,
            "c_ClubTeamNatio": "Armenië",
            "c_ClubTeamNatioShort": "ARM",
            "n_ClubTeamFunctionType": 4,
            "c_ClubTeamFunction": "Middenvelder",
            "c_ClubTeamFunctionShort": "M",
            "n_ClubTeamFunctionCode": 4,
            "n_NatTeamID": 3093,
            "c_NatTeam": "Armenië",
            "n_NatTeamFunctionType": 4,
            "c_NatTeamFunction": "Middenvelder",
            "c_NatTeamFunctionShort": "M",
            "n_NatTeamFunctionCode": 4
        }
    ],
    "PlayerLeague": [
        {
            "n_CompetitionID": 2,
            "n_CompetitionLevel": 1,
            "c_Competition": "Eredivisie",
            "c_CompetitionShort": "Ere",
            "n_CompetitionNatioGeoID": 2201,
            "c_CompetitionNatio": "Nederland",
            "c_CompetitionNatioShort": "NED",
            "c_Season": "2010/2011",
            "n_EditionID": 18090,
            "c_Edition": "2010/2011",
            "d_EditionStartDate": "/Date(1277935200000+0200)/",
            "d_EditionEndDate": "/Date(1309384800000+0200)/",
            "n_PersonNatioGeoID": 2201,
            "n_TeamID": 2,
            "c_Team": "Ajax",
            "c_TeamShort": "AJA",
            "n_TeamNatioGeoID": 2201,
            "c_TeamNatio": "Nederland",
            "c_TeamNatioShort": "NED",
            "n_FunctionType": 8,
            "c_Function": "Aanvaller",
            "c_FunctionShort": "A",
            "n_FunctionCode": 8,
            "n_DateSort": 20100701,
            "n_Matches": 14,
            "n_MatchesStart": 3,
            "n_MatchesOut": 3,
            "n_MatchesIn": 11,
            "n_MinutesPlayed": 430,
            "n_Goals": 1,
            "n_OwnGoals": 0,
            "n_Assists": 1,
            "n_CardsRedDirect": 0,
            "n_CardsRed2Yellow": 0,
            "n_CardsRed": 0,
            "n_CardsYellow": 5
        },
        {
            "n_CompetitionID": 2,
            "n_CompetitionLevel": 1,
            "c_Competition": "Eredivisie",
            "c_CompetitionShort": "Ere",
            "n_CompetitionNatioGeoID": 2201,
            "c_CompetitionNatio": "Nederland",
            "c_CompetitionNatioShort": "NED",
            "c_Season": "2011/2012",
            "n_EditionID": 18803,
            "c_Edition": "2011/2012",
            "d_EditionStartDate": "/Date(1309471200000+0200)/",
            "d_EditionEndDate": "/Date(1341007200000+0200)/",
            "n_PersonNatioGeoID": 4317,
            "n_TeamID": 2,
            "c_Team": "Ajax",
            "c_TeamShort": "AJA",
            "n_TeamNatioGeoID": 2201,
            "c_TeamNatio": "Nederland",
            "c_TeamNatioShort": "NED",
            "n_FunctionType": 8,
            "c_Function": "Aanvaller",
            "c_FunctionShort": "A",
            "n_FunctionCode": 8,
            "n_DateSort": 20100701,
            "n_Matches": 12,
            "n_MatchesStart": 10,
            "n_MatchesOut": 7,
            "n_MatchesIn": 2,
            "n_MinutesPlayed": 732,
            "n_Goals": 1,
            "n_OwnGoals": 0,
            "n_Assists": 1,
            "n_CardsRedDirect": 0,
            "n_CardsRed2Yellow": 0,
            "n_CardsRed": 0,
            "n_CardsYellow": 0
        },
        {
            "n_CompetitionID": 76,
            "n_CompetitionLevel": 1,
            "c_Competition": "SOGAZ Russian Football Championship",
            "c_CompetitionShort": null,
            "n_CompetitionNatioGeoID": 2204,
            "c_CompetitionNatio": "Rusland",
            "c_CompetitionNatioShort": "RUS",
            "c_Season": "2012/2013",
            "n_EditionID": 19664,
            "c_Edition": "2012/2013",
            "d_EditionStartDate": "/Date(1341093600000+0200)/",
            "d_EditionEndDate": "/Date(1372543200000+0200)/",
            "n_PersonNatioGeoID": 4317,
            "n_TeamID": 105426,
            "c_Team": "Koeban Krasnodar",
            "c_TeamShort": "KKR",
            "n_TeamNatioGeoID": 2204,
            "c_TeamNatio": "Rusland",
            "c_TeamNatioShort": "RUS",
            "n_FunctionType": 8,
            "c_Function": "Aanvaller",
            "c_FunctionShort": "A",
            "n_FunctionCode": 8,
            "n_DateSort": 20120809,
            "n_Matches": 22,
            "n_MatchesStart": 16,
            "n_MatchesOut": 10,
            "n_MatchesIn": 6,
            "n_MinutesPlayed": 1395,
            "n_Goals": 9,
            "n_OwnGoals": 1,
            "n_Assists": null,
            "n_CardsRedDirect": 0,
            "n_CardsRed2Yellow": 0,
            "n_CardsRed": 0,
            "n_CardsYellow": 4
        },
        {
            "n_CompetitionID": 76,
            "n_CompetitionLevel": 1,
            "c_Competition": "SOGAZ Russian Football Championship",
            "c_CompetitionShort": null,
            "n_CompetitionNatioGeoID": 2204,
            "c_CompetitionNatio": "Rusland",
            "c_CompetitionNatioShort": "RUS",
            "c_Season": "2013/2014",
            "n_EditionID": 20618,
            "c_Edition": "2013/2014",
            "d_EditionStartDate": "/Date(1372629600000+0200)/",
            "d_EditionEndDate": "/Date(1404079200000+0200)/",
            "n_PersonNatioGeoID": 4317,
            "n_TeamID": 105426,
            "c_Team": "Koeban Krasnodar",
            "c_TeamShort": "KKR",
            "n_TeamNatioGeoID": 2204,
            "c_TeamNatio": "Rusland",
            "c_TeamNatioShort": "RUS",
            "n_FunctionType": 8,
            "c_Function": "Aanvaller",
            "c_FunctionShort": "A",
            "n_FunctionCode": 8,
            "n_DateSort": 20120809,
            "n_Matches": 2,
            "n_MatchesStart": 2,
            "n_MatchesOut": 1,
            "n_MatchesIn": 0,
            "n_MinutesPlayed": 172,
            "n_Goals": 2,
            "n_OwnGoals": 0,
            "n_Assists": null,
            "n_CardsRedDirect": 0,
            "n_CardsRed2Yellow": 0,
            "n_CardsRed": 0,
            "n_CardsYellow": 0
        },
        {
            "n_CompetitionID": 76,
            "n_CompetitionLevel": 1,
            "c_Competition": "SOGAZ Russian Football Championship",
            "c_CompetitionShort": null,
            "n_CompetitionNatioGeoID": 2204,
            "c_CompetitionNatio": "Rusland",
            "c_CompetitionNatioShort": "RUS",
            "c_Season": "2013/2014",
            "n_EditionID": 20618,
            "c_Edition": "2013/2014",
            "d_EditionStartDate": "/Date(1372629600000+0200)/",
            "d_EditionEndDate": "/Date(1404079200000+0200)/",
            "n_PersonNatioGeoID": 4317,
            "n_TeamID": 4120,
            "c_Team": "Spartak Moskou",
            "c_TeamShort": "SPM",
            "n_TeamNatioGeoID": 2204,
            "c_TeamNatio": "Rusland",
            "c_TeamNatioShort": "RUS",
            "n_FunctionType": 8,
            "c_Function": "Aanvaller",
            "c_FunctionShort": "A",
            "n_FunctionCode": 8,
            "n_DateSort": 20130726,
            "n_Matches": 27,
            "n_MatchesStart": 18,
            "n_MatchesOut": 10,
            "n_MatchesIn": 9,
            "n_MinutesPlayed": 1670,
            "n_Goals": 3,
            "n_OwnGoals": 0,
            "n_Assists": null,
            "n_CardsRedDirect": 0,
            "n_CardsRed2Yellow": 0,
            "n_CardsRed": 0,
            "n_CardsYellow": 2
        },
        {
            "n_CompetitionID": 76,
            "n_CompetitionLevel": 1,
            "c_Competition": "SOGAZ Russian Football Championship",
            "c_CompetitionShort": null,
            "n_CompetitionNatioGeoID": 2204,
            "c_CompetitionNatio": "Rusland",
            "c_CompetitionNatioShort": "RUS",
            "c_Season": "2014/2015",
            "n_EditionID": 21186,
            "c_Edition": "2014/2015",
            "d_EditionStartDate": "/Date(1404165600000+0200)/",
            "d_EditionEndDate": "/Date(1435615200000+0200)/",
            "n_PersonNatioGeoID": 4317,
            "n_TeamID": 4120,
            "c_Team": "Spartak Moskou",
            "c_TeamShort": "SPM",
            "n_TeamNatioGeoID": 2204,
            "c_TeamNatio": "Rusland",
            "c_TeamNatioShort": "RUS",
            "n_FunctionType": 8,
            "c_Function": "Aanvaller",
            "c_FunctionShort": "A",
            "n_FunctionCode": 8,
            "n_DateSort": 20130726,
            "n_Matches": 1,
            "n_MatchesStart": 0,
            "n_MatchesOut": 0,
            "n_MatchesIn": 1,
            "n_MinutesPlayed": 18,
            "n_Goals": 0,
            "n_OwnGoals": 0,
            "n_Assists": null,
            "n_CardsRedDirect": 0,
            "n_CardsRed2Yellow": 0,
            "n_CardsRed": 0,
            "n_CardsYellow": 0
        },
        {
            "n_CompetitionID": 76,
            "n_CompetitionLevel": 1,
            "c_Competition": "Rosgosstrakh Russian Football Championship",
            "c_CompetitionShort": null,
            "n_CompetitionNatioGeoID": 2204,
            "c_CompetitionNatio": "Rusland",
            "c_CompetitionNatioShort": "RUS",
            "c_Season": "2015/2016",
            "n_EditionID": 21752,
            "c_Edition": "2015/2016",
            "d_EditionStartDate": "/Date(1435701600000+0200)/",
            "d_EditionEndDate": "/Date(1467237600000+0200)/",
            "n_PersonNatioGeoID": 4317,
            "n_TeamID": 4120,
            "c_Team": "Spartak Moskou",
            "c_TeamShort": "SPM",
            "n_TeamNatioGeoID": 2204,
            "c_TeamNatio": "Rusland",
            "c_TeamNatioShort": "RUS",
            "n_FunctionType": 8,
            "c_Function": "Aanvaller",
            "c_FunctionShort": "A",
            "n_FunctionCode": 8,
            "n_DateSort": 20130726,
            "n_Matches": 7,
            "n_MatchesStart": 1,
            "n_MatchesOut": 1,
            "n_MatchesIn": 6,
            "n_MinutesPlayed": 216,
            "n_Goals": 0,
            "n_OwnGoals": 0,
            "n_Assists": null,
            "n_CardsRedDirect": 0,
            "n_CardsRed2Yellow": 0,
            "n_CardsRed": 0,
            "n_CardsYellow": 3
        },
        {
            "n_CompetitionID": 67,
            "n_CompetitionLevel": 1,
            "c_Competition": "Liga BBVA",
            "c_CompetitionShort": null,
            "n_CompetitionNatioGeoID": 2203,
            "c_CompetitionNatio": "Spanje",
            "c_CompetitionNatioShort": "SPA",
            "c_Season": "2015/2016",
            "n_EditionID": 21737,
            "c_Edition": "2015/2016",
            "d_EditionStartDate": "/Date(1435701600000+0200)/",
            "d_EditionEndDate": "/Date(1467237600000+0200)/",
            "n_PersonNatioGeoID": 4317,
            "n_TeamID": 100009,
            "c_Team": "Rayo Vallecano",
            "c_TeamShort": "RAY",
            "n_TeamNatioGeoID": 2203,
            "c_TeamNatio": "Spanje",
            "c_TeamNatioShort": "SPA",
            "n_FunctionType": 8,
            "c_Function": "Aanvaller",
            "c_FunctionShort": "A",
            "n_FunctionCode": 8,
            "n_DateSort": 20160127,
            "n_Matches": 3,
            "n_MatchesStart": 1,
            "n_MatchesOut": 1,
            "n_MatchesIn": 2,
            "n_MinutesPlayed": 99,
            "n_Goals": 0,
            "n_OwnGoals": 0,
            "n_Assists": null,
            "n_CardsRedDirect": 0,
            "n_CardsRed2Yellow": 0,
            "n_CardsRed": 0,
            "n_CardsYellow": 1
        },
        {
            "n_CompetitionID": 57,
            "n_CompetitionLevel": 1,
            "c_Competition": "Spor Toto Süper Lig",
            "c_CompetitionShort": null,
            "n_CompetitionNatioGeoID": 2786,
            "c_CompetitionNatio": "Turkije",
            "c_CompetitionNatioShort": "TUR",
            "c_Season": "2016/2017",
            "n_EditionID": 22337,
            "c_Edition": "2016/2017",
            "d_EditionStartDate": "/Date(1467324000000+0200)/",
            "d_EditionEndDate": "/Date(1498773600000+0200)/",
            "n_PersonNatioGeoID": 4317,
            "n_TeamID": 4020,
            "c_Team": "Besiktas",
            "c_TeamShort": "BES",
            "n_TeamNatioGeoID": 2786,
            "c_TeamNatio": "Turkije",
            "c_TeamNatioShort": "TUR",
            "n_FunctionType": 8,
            "c_Function": "Aanvaller",
            "c_FunctionShort": "A",
            "n_FunctionCode": 8,
            "n_DateSort": 20160701,
            "n_Matches": 1,
            "n_MatchesStart": 0,
            "n_MatchesOut": 0,
            "n_MatchesIn": 1,
            "n_MinutesPlayed": 7,
            "n_Goals": 0,
            "n_OwnGoals": 0,
            "n_Assists": null,
            "n_CardsRedDirect": 0,
            "n_CardsRed2Yellow": 0,
            "n_CardsRed": 0,
            "n_CardsYellow": 0
        },
        {
            "n_CompetitionID": 57,
            "n_CompetitionLevel": 1,
            "c_Competition": "Spor Toto Süper Lig",
            "c_CompetitionShort": null,
            "n_CompetitionNatioGeoID": 2786,
            "c_CompetitionNatio": "Turkije",
            "c_CompetitionNatioShort": "TUR",
            "c_Season": "2017/2018",
            "n_EditionID": 22922,
            "c_Edition": "2017/2018",
            "d_EditionStartDate": "/Date(1498860000000+0200)/",
            "d_EditionEndDate": "/Date(1530309600000+0200)/",
            "n_PersonNatioGeoID": 4317,
            "n_TeamID": 4020,
            "c_Team": "Besiktas",
            "c_TeamShort": "BES",
            "n_TeamNatioGeoID": 2786,
            "c_TeamNatio": "Turkije",
            "c_TeamNatioShort": "TUR",
            "n_FunctionType": 8,
            "c_Function": "Aanvaller",
            "c_FunctionShort": "A",
            "n_FunctionCode": 8,
            "n_DateSort": 20160701,
            "n_Matches": 0,
            "n_MatchesStart": 0,
            "n_MatchesOut": 0,
            "n_MatchesIn": 0,
            "n_MinutesPlayed": 0,
            "n_Goals": 0,
            "n_OwnGoals": 0,
            "n_Assists": null,
            "n_CardsRedDirect": 0,
            "n_CardsRed2Yellow": 0,
            "n_CardsRed": 0,
            "n_CardsYellow": 0
        },
        {
            "n_CompetitionID": 2,
            "n_CompetitionLevel": 1,
            "c_Competition": "Eredivisie",
            "c_CompetitionShort": "Ere",
            "n_CompetitionNatioGeoID": 2201,
            "c_CompetitionNatio": "Nederland",
            "c_CompetitionNatioShort": "NED",
            "c_Season": "2018/2019",
            "n_EditionID": 23521,
            "c_Edition": "2018/2019",
            "d_EditionStartDate": "/Date(1530396000000+0200)/",
            "d_EditionEndDate": "/Date(1561845600000+0200)/",
            "n_PersonNatioGeoID": 4317,
            "n_TeamID": 19,
            "c_Team": "Willem II",
            "c_TeamShort": "WIL",
            "n_TeamNatioGeoID": 2201,
            "c_TeamNatio": "Nederland",
            "c_TeamNatioShort": "NED",
            "n_FunctionType": 8,
            "c_Function": "Aanvaller",
            "c_FunctionShort": "A",
            "n_FunctionCode": 8,
            "n_DateSort": 20180815,
            "n_Matches": 14,
            "n_MatchesStart": 10,
            "n_MatchesOut": 6,
            "n_MatchesIn": 4,
            "n_MinutesPlayed": 883,
            "n_Goals": 1,
            "n_OwnGoals": 0,
            "n_Assists": 2,
            "n_CardsRedDirect": 0,
            "n_CardsRed2Yellow": 0,
            "n_CardsRed": 0,
            "n_CardsYellow": 2
        },
        {
            "n_CompetitionID": 57,
            "n_CompetitionLevel": 1,
            "c_Competition": "Spor Toto Süper Lig",
            "c_CompetitionShort": null,
            "n_CompetitionNatioGeoID": 2786,
            "c_CompetitionNatio": "Turkije",
            "c_CompetitionNatioShort": "TUR",
            "c_Season": "2018/2019",
            "n_EditionID": 23516,
            "c_Edition": "2018/2019",
            "d_EditionStartDate": "/Date(1530396000000+0200)/",
            "d_EditionEndDate": "/Date(1561845600000+0200)/",
            "n_PersonNatioGeoID": 4317,
            "n_TeamID": 4020,
            "c_Team": "Besiktas",
            "c_TeamShort": "BES",
            "n_TeamNatioGeoID": 2786,
            "c_TeamNatio": "Turkije",
            "c_TeamNatioShort": "TUR",
            "n_FunctionType": 8,
            "c_Function": "Aanvaller",
            "c_FunctionShort": "A",
            "n_FunctionCode": 8,
            "n_DateSort": 20190405,
            "n_Matches": 0,
            "n_MatchesStart": 0,
            "n_MatchesOut": 0,
            "n_MatchesIn": 0,
            "n_MinutesPlayed": 0,
            "n_Goals": 0,
            "n_OwnGoals": 0,
            "n_Assists": null,
            "n_CardsRedDirect": 0,
            "n_CardsRed2Yellow": 0,
            "n_CardsRed": 0,
            "n_CardsYellow": 0
        }
    ],
    "PlayerCup": [
        {
            "n_CompetitionID": 3,
            "n_CompetitionLevel": 0,
            "c_Competition": "Johan Cruijff Schaal",
            "c_CompetitionShort": null,
            "n_CompetitionNatioGeoID": 2201,
            "c_CompetitionNatio": "Nederland",
            "c_CompetitionNatioShort": "NED",
            "c_Season": "2010/2011",
            "n_EditionID": 17806,
            "c_Edition": "2010",
            "d_EditionStartDate": "/Date(1277935200000+0200)/",
            "d_EditionEndDate": "/Date(1309384800000+0200)/",
            "n_PersonNatioGeoID": 2201,
            "n_TeamID": 2,
            "c_Team": "Ajax",
            "c_TeamShort": "AJA",
            "n_TeamNatioGeoID": 2201,
            "c_TeamNatio": "Nederland",
            "c_TeamNatioShort": "NED",
            "n_FunctionType": 8,
            "c_Function": "Aanvaller",
            "c_FunctionShort": "A",
            "n_FunctionCode": 8,
            "n_DateSort": 20100701,
            "n_Matches": 0,
            "n_MatchesStart": 0,
            "n_MatchesOut": 0,
            "n_MatchesIn": 0,
            "n_MinutesPlayed": 0,
            "n_Goals": 0,
            "n_OwnGoals": 0,
            "n_Assists": null,
            "n_CardsRedDirect": 0,
            "n_CardsRed2Yellow": 0,
            "n_CardsRed": 0,
            "n_CardsYellow": 0
        },
        {
            "n_CompetitionID": 4,
            "n_CompetitionLevel": 1,
            "c_Competition": "KNVB Beker",
            "c_CompetitionShort": "KNVB",
            "n_CompetitionNatioGeoID": 2201,
            "c_CompetitionNatio": "Nederland",
            "c_CompetitionNatioShort": "NED",
            "c_Season": "2010/2011",
            "n_EditionID": 18259,
            "c_Edition": "2010/2011",
            "d_EditionStartDate": "/Date(1277935200000+0200)/",
            "d_EditionEndDate": "/Date(1309384800000+0200)/",
            "n_PersonNatioGeoID": 2201,
            "n_TeamID": 2,
            "c_Team": "Ajax",
            "c_TeamShort": "AJA",
            "n_TeamNatioGeoID": 2201,
            "c_TeamNatio": "Nederland",
            "c_TeamNatioShort": "NED",
            "n_FunctionType": 8,
            "c_Function": "Aanvaller",
            "c_FunctionShort": "A",
            "n_FunctionCode": 8,
            "n_DateSort": 20100701,
            "n_Matches": 3,
            "n_MatchesStart": 0,
            "n_MatchesOut": 0,
            "n_MatchesIn": 3,
            "n_MinutesPlayed": 26,
            "n_Goals": 0,
            "n_OwnGoals": 0,
            "n_Assists": null,
            "n_CardsRedDirect": 0,
            "n_CardsRed2Yellow": 0,
            "n_CardsRed": 0,
            "n_CardsYellow": 0
        },
        {
            "n_CompetitionID": 3,
            "n_CompetitionLevel": 0,
            "c_Competition": "Johan Cruijff Schaal",
            "c_CompetitionShort": null,
            "n_CompetitionNatioGeoID": 2201,
            "c_CompetitionNatio": "Nederland",
            "c_CompetitionNatioShort": "NED",
            "c_Season": "2011/2012",
            "n_EditionID": 18740,
            "c_Edition": "2011",
            "d_EditionStartDate": "/Date(1309471200000+0200)/",
            "d_EditionEndDate": "/Date(1341007200000+0200)/",
            "n_PersonNatioGeoID": 4317,
            "n_TeamID": 2,
            "c_Team": "Ajax",
            "c_TeamShort": "AJA",
            "n_TeamNatioGeoID": 2201,
            "c_TeamNatio": "Nederland",
            "c_TeamNatioShort": "NED",
            "n_FunctionType": 8,
            "c_Function": "Aanvaller",
            "c_FunctionShort": "A",
            "n_FunctionCode": 8,
            "n_DateSort": 20100701,
            "n_Matches": 0,
            "n_MatchesStart": 0,
            "n_MatchesOut": 0,
            "n_MatchesIn": 0,
            "n_MinutesPlayed": 0,
            "n_Goals": 0,
            "n_OwnGoals": 0,
            "n_Assists": null,
            "n_CardsRedDirect": 0,
            "n_CardsRed2Yellow": 0,
            "n_CardsRed": 0,
            "n_CardsYellow": 0
        },
        {
            "n_CompetitionID": 4,
            "n_CompetitionLevel": 1,
            "c_Competition": "KNVB Beker",
            "c_CompetitionShort": "KNVB",
            "n_CompetitionNatioGeoID": 2201,
            "c_CompetitionNatio": "Nederland",
            "c_CompetitionNatioShort": "NED",
            "c_Season": "2011/2012",
            "n_EditionID": 18834,
            "c_Edition": "2011/2012",
            "d_EditionStartDate": "/Date(1309471200000+0200)/",
            "d_EditionEndDate": "/Date(1341007200000+0200)/",
            "n_PersonNatioGeoID": 4317,
            "n_TeamID": 2,
            "c_Team": "Ajax",
            "c_TeamShort": "AJA",
            "n_TeamNatioGeoID": 2201,
            "c_TeamNatio": "Nederland",
            "c_TeamNatioShort": "NED",
            "n_FunctionType": 8,
            "c_Function": "Aanvaller",
            "c_FunctionShort": "A",
            "n_FunctionCode": 8,
            "n_DateSort": 20100701,
            "n_Matches": 2,
            "n_MatchesStart": 1,
            "n_MatchesOut": 1,
            "n_MatchesIn": 1,
            "n_MinutesPlayed": 52,
            "n_Goals": 0,
            "n_OwnGoals": 0,
            "n_Assists": null,
            "n_CardsRedDirect": 0,
            "n_CardsRed2Yellow": 0,
            "n_CardsRed": 0,
            "n_CardsYellow": 0
        },
        {
            "n_CompetitionID": 3,
            "n_CompetitionLevel": 0,
            "c_Competition": "Johan Cruijff Schaal",
            "c_CompetitionShort": null,
            "n_CompetitionNatioGeoID": 2201,
            "c_CompetitionNatio": "Nederland",
            "c_CompetitionNatioShort": "NED",
            "c_Season": "2012/2013",
            "n_EditionID": 19705,
            "c_Edition": "2012",
            "d_EditionStartDate": "/Date(1341093600000+0200)/",
            "d_EditionEndDate": "/Date(1372543200000+0200)/",
            "n_PersonNatioGeoID": 4317,
            "n_TeamID": 2,
            "c_Team": "Ajax",
            "c_TeamShort": "AJA",
            "n_TeamNatioGeoID": 2201,
            "c_TeamNatio": "Nederland",
            "c_TeamNatioShort": "NED",
            "n_FunctionType": 8,
            "c_Function": "Aanvaller",
            "c_FunctionShort": "A",
            "n_FunctionCode": 8,
            "n_DateSort": 20100701,
            "n_Matches": 1,
            "n_MatchesStart": 1,
            "n_MatchesOut": 0,
            "n_MatchesIn": 0,
            "n_MinutesPlayed": 90,
            "n_Goals": 0,
            "n_OwnGoals": 0,
            "n_Assists": null,
            "n_CardsRedDirect": 0,
            "n_CardsRed2Yellow": 0,
            "n_CardsRed": 0,
            "n_CardsYellow": 0
        },
        {
            "n_CompetitionID": 349,
            "n_CompetitionLevel": 1,
            "c_Competition": "Russische Beker",
            "c_CompetitionShort": null,
            "n_CompetitionNatioGeoID": 2204,
            "c_CompetitionNatio": "Rusland",
            "c_CompetitionNatioShort": "RUS",
            "c_Season": "2012/2013",
            "n_EditionID": 19920,
            "c_Edition": "2012/2013",
            "d_EditionStartDate": "/Date(1341093600000+0200)/",
            "d_EditionEndDate": "/Date(1372543200000+0200)/",
            "n_PersonNatioGeoID": 4317,
            "n_TeamID": 105426,
            "c_Team": "Koeban Krasnodar",
            "c_TeamShort": "KKR",
            "n_TeamNatioGeoID": 2204,
            "c_TeamNatio": "Rusland",
            "c_TeamNatioShort": "RUS",
            "n_FunctionType": 8,
            "c_Function": "Aanvaller",
            "c_FunctionShort": "A",
            "n_FunctionCode": 8,
            "n_DateSort": 20120809,
            "n_Matches": 0,
            "n_MatchesStart": 0,
            "n_MatchesOut": 0,
            "n_MatchesIn": 0,
            "n_MinutesPlayed": 0,
            "n_Goals": 0,
            "n_OwnGoals": 0,
            "n_Assists": null,
            "n_CardsRedDirect": 0,
            "n_CardsRed2Yellow": 0,
            "n_CardsRed": 0,
            "n_CardsYellow": 0
        },
        {
            "n_CompetitionID": 349,
            "n_CompetitionLevel": 1,
            "c_Competition": "Russische Beker",
            "c_CompetitionShort": null,
            "n_CompetitionNatioGeoID": 2204,
            "c_CompetitionNatio": "Rusland",
            "c_CompetitionNatioShort": "RUS",
            "c_Season": "2013/2014",
            "n_EditionID": 20619,
            "c_Edition": "2013/2014",
            "d_EditionStartDate": "/Date(1372629600000+0200)/",
            "d_EditionEndDate": "/Date(1404079200000+0200)/",
            "n_PersonNatioGeoID": 4317,
            "n_TeamID": 4120,
            "c_Team": "Spartak Moskou",
            "c_TeamShort": "SPM",
            "n_TeamNatioGeoID": 2204,
            "c_TeamNatio": "Rusland",
            "c_TeamNatioShort": "RUS",
            "n_FunctionType": 8,
            "c_Function": "Aanvaller",
            "c_FunctionShort": "A",
            "n_FunctionCode": 8,
            "n_DateSort": 20130726,
            "n_Matches": 0,
            "n_MatchesStart": 0,
            "n_MatchesOut": 0,
            "n_MatchesIn": 0,
            "n_MinutesPlayed": 0,
            "n_Goals": 0,
            "n_OwnGoals": 0,
            "n_Assists": null,
            "n_CardsRedDirect": 0,
            "n_CardsRed2Yellow": 0,
            "n_CardsRed": 0,
            "n_CardsYellow": 0
        },
        {
            "n_CompetitionID": 349,
            "n_CompetitionLevel": 1,
            "c_Competition": "Russische Beker",
            "c_CompetitionShort": null,
            "n_CompetitionNatioGeoID": 2204,
            "c_CompetitionNatio": "Rusland",
            "c_CompetitionNatioShort": "RUS",
            "c_Season": "2014/2015",
            "n_EditionID": 21290,
            "c_Edition": "2014/2015",
            "d_EditionStartDate": "/Date(1404165600000+0200)/",
            "d_EditionEndDate": "/Date(1435615200000+0200)/",
            "n_PersonNatioGeoID": 4317,
            "n_TeamID": 4120,
            "c_Team": "Spartak Moskou",
            "c_TeamShort": "SPM",
            "n_TeamNatioGeoID": 2204,
            "c_TeamNatio": "Rusland",
            "c_TeamNatioShort": "RUS",
            "n_FunctionType": 8,
            "c_Function": "Aanvaller",
            "c_FunctionShort": "A",
            "n_FunctionCode": 8,
            "n_DateSort": 20130726,
            "n_Matches": 0,
            "n_MatchesStart": 0,
            "n_MatchesOut": 0,
            "n_MatchesIn": 0,
            "n_MinutesPlayed": 0,
            "n_Goals": 0,
            "n_OwnGoals": 0,
            "n_Assists": null,
            "n_CardsRedDirect": 0,
            "n_CardsRed2Yellow": 0,
            "n_CardsRed": 0,
            "n_CardsYellow": 0
        },
        {
            "n_CompetitionID": 349,
            "n_CompetitionLevel": 1,
            "c_Competition": "Russische Beker",
            "c_CompetitionShort": null,
            "n_CompetitionNatioGeoID": 2204,
            "c_CompetitionNatio": "Rusland",
            "c_CompetitionNatioShort": "RUS",
            "c_Season": "2015/2016",
            "n_EditionID": 21849,
            "c_Edition": "2015/2016",
            "d_EditionStartDate": "/Date(1435701600000+0200)/",
            "d_EditionEndDate": "/Date(1467237600000+0200)/",
            "n_PersonNatioGeoID": 4317,
            "n_TeamID": 4120,
            "c_Team": "Spartak Moskou",
            "c_TeamShort": "SPM",
            "n_TeamNatioGeoID": 2204,
            "c_TeamNatio": "Rusland",
            "c_TeamNatioShort": "RUS",
            "n_FunctionType": 8,
            "c_Function": "Aanvaller",
            "c_FunctionShort": "A",
            "n_FunctionCode": 8,
            "n_DateSort": 20130726,
            "n_Matches": 0,
            "n_MatchesStart": 0,
            "n_MatchesOut": 0,
            "n_MatchesIn": 0,
            "n_MinutesPlayed": 0,
            "n_Goals": 1,
            "n_OwnGoals": 0,
            "n_Assists": null,
            "n_CardsRedDirect": 0,
            "n_CardsRed2Yellow": 0,
            "n_CardsRed": 0,
            "n_CardsYellow": 0
        },
        {
            "n_CompetitionID": 654,
            "n_CompetitionLevel": 0,
            "c_Competition": "Turkcell Süper Kupa",
            "c_CompetitionShort": null,
            "n_CompetitionNatioGeoID": 2786,
            "c_CompetitionNatio": "Turkije",
            "c_CompetitionNatioShort": "TUR",
            "c_Season": "2016/2017",
            "n_EditionID": 22135,
            "c_Edition": "2016",
            "d_EditionStartDate": "/Date(1467324000000+0200)/",
            "d_EditionEndDate": "/Date(1498773600000+0200)/",
            "n_PersonNatioGeoID": 4317,
            "n_TeamID": 4020,
            "c_Team": "Besiktas",
            "c_TeamShort": "BES",
            "n_TeamNatioGeoID": 2786,
            "c_TeamNatio": "Turkije",
            "c_TeamNatioShort": "TUR",
            "n_FunctionType": 8,
            "c_Function": "Aanvaller",
            "c_FunctionShort": "A",
            "n_FunctionCode": 8,
            "n_DateSort": 20160701,
            "n_Matches": 0,
            "n_MatchesStart": 0,
            "n_MatchesOut": 0,
            "n_MatchesIn": 0,
            "n_MinutesPlayed": 0,
            "n_Goals": 0,
            "n_OwnGoals": 0,
            "n_Assists": null,
            "n_CardsRedDirect": 0,
            "n_CardsRed2Yellow": 0,
            "n_CardsRed": 0,
            "n_CardsYellow": 0
        },
        {
            "n_CompetitionID": 63,
            "n_CompetitionLevel": 1,
            "c_Competition": "Ziraat Türkiye Kupasi",
            "c_CompetitionShort": null,
            "n_CompetitionNatioGeoID": 2786,
            "c_CompetitionNatio": "Turkije",
            "c_CompetitionNatioShort": "TUR",
            "c_Season": "2016/2017",
            "n_EditionID": 22343,
            "c_Edition": "2016/2017",
            "d_EditionStartDate": "/Date(1467324000000+0200)/",
            "d_EditionEndDate": "/Date(1498773600000+0200)/",
            "n_PersonNatioGeoID": 4317,
            "n_TeamID": 4020,
            "c_Team": "Besiktas",
            "c_TeamShort": "BES",
            "n_TeamNatioGeoID": 2786,
            "c_TeamNatio": "Turkije",
            "c_TeamNatioShort": "TUR",
            "n_FunctionType": 8,
            "c_Function": "Aanvaller",
            "c_FunctionShort": "A",
            "n_FunctionCode": 8,
            "n_DateSort": 20160701,
            "n_Matches": 3,
            "n_MatchesStart": 2,
            "n_MatchesOut": 0,
            "n_MatchesIn": 1,
            "n_MinutesPlayed": 211,
            "n_Goals": 0,
            "n_OwnGoals": 0,
            "n_Assists": null,
            "n_CardsRedDirect": 0,
            "n_CardsRed2Yellow": 0,
            "n_CardsRed": 0,
            "n_CardsYellow": 1
        },
        {
            "n_CompetitionID": 654,
            "n_CompetitionLevel": 0,
            "c_Competition": "Turkcell Süper Kupa",
            "c_CompetitionShort": null,
            "n_CompetitionNatioGeoID": 2786,
            "c_CompetitionNatio": "Turkije",
            "c_CompetitionNatioShort": "TUR",
            "c_Season": "2017/2018",
            "n_EditionID": 22762,
            "c_Edition": "2017",
            "d_EditionStartDate": "/Date(1498860000000+0200)/",
            "d_EditionEndDate": "/Date(1530309600000+0200)/",
            "n_PersonNatioGeoID": 4317,
            "n_TeamID": 4020,
            "c_Team": "Besiktas",
            "c_TeamShort": "BES",
            "n_TeamNatioGeoID": 2786,
            "c_TeamNatio": "Turkije",
            "c_TeamNatioShort": "TUR",
            "n_FunctionType": 8,
            "c_Function": "Aanvaller",
            "c_FunctionShort": "A",
            "n_FunctionCode": 8,
            "n_DateSort": 20160701,
            "n_Matches": 0,
            "n_MatchesStart": 0,
            "n_MatchesOut": 0,
            "n_MatchesIn": 0,
            "n_MinutesPlayed": 0,
            "n_Goals": 0,
            "n_OwnGoals": 0,
            "n_Assists": null,
            "n_CardsRedDirect": 0,
            "n_CardsRed2Yellow": 0,
            "n_CardsRed": 0,
            "n_CardsYellow": 0
        },
        {
            "n_CompetitionID": 63,
            "n_CompetitionLevel": 1,
            "c_Competition": "Ziraat Türkiye Kupasi",
            "c_CompetitionShort": null,
            "n_CompetitionNatioGeoID": 2786,
            "c_CompetitionNatio": "Turkije",
            "c_CompetitionNatioShort": "TUR",
            "c_Season": "2017/2018",
            "n_EditionID": 22949,
            "c_Edition": "2017/2018",
            "d_EditionStartDate": "/Date(1498860000000+0200)/",
            "d_EditionEndDate": "/Date(1530309600000+0200)/",
            "n_PersonNatioGeoID": 4317,
            "n_TeamID": 4020,
            "c_Team": "Besiktas",
            "c_TeamShort": "BES",
            "n_TeamNatioGeoID": 2786,
            "c_TeamNatio": "Turkije",
            "c_TeamNatioShort": "TUR",
            "n_FunctionType": 8,
            "c_Function": "Aanvaller",
            "c_FunctionShort": "A",
            "n_FunctionCode": 8,
            "n_DateSort": 20160701,
            "n_Matches": 1,
            "n_MatchesStart": 1,
            "n_MatchesOut": 1,
            "n_MatchesIn": 0,
            "n_MinutesPlayed": 37,
            "n_Goals": 1,
            "n_OwnGoals": 0,
            "n_Assists": null,
            "n_CardsRedDirect": 0,
            "n_CardsRed2Yellow": 0,
            "n_CardsRed": 0,
            "n_CardsYellow": 0
        },
        {
            "n_CompetitionID": 4,
            "n_CompetitionLevel": 1,
            "c_Competition": "TOTO KNVB Beker",
            "c_CompetitionShort": "KNVB",
            "n_CompetitionNatioGeoID": 2201,
            "c_CompetitionNatio": "Nederland",
            "c_CompetitionNatioShort": "NED",
            "c_Season": "2018/2019",
            "n_EditionID": 23543,
            "c_Edition": "2018/2019",
            "d_EditionStartDate": "/Date(1530396000000+0200)/",
            "d_EditionEndDate": "/Date(1561845600000+0200)/",
            "n_PersonNatioGeoID": 4317,
            "n_TeamID": 19,
            "c_Team": "Willem II",
            "c_TeamShort": "WIL",
            "n_TeamNatioGeoID": 2201,
            "c_TeamNatio": "Nederland",
            "c_TeamNatioShort": "NED",
            "n_FunctionType": 8,
            "c_Function": "Aanvaller",
            "c_FunctionShort": "A",
            "n_FunctionCode": 8,
            "n_DateSort": 20180815,
            "n_Matches": 3,
            "n_MatchesStart": 3,
            "n_MatchesOut": 3,
            "n_MatchesIn": 0,
            "n_MinutesPlayed": 183,
            "n_Goals": 1,
            "n_OwnGoals": 0,
            "n_Assists": null,
            "n_CardsRedDirect": 0,
            "n_CardsRed2Yellow": 0,
            "n_CardsRed": 0,
            "n_CardsYellow": 0
        }
    ],
    "PlayerInternationalclub": [
        {
            "n_CompetitionID": 41,
            "n_CompetitionLevel": 0,
            "c_Competition": "UEFA Champions League",
            "c_CompetitionShort": "Ch. League",
            "n_CompetitionNatioGeoID": 2101,
            "c_CompetitionNatio": "Europa",
            "c_CompetitionNatioShort": "EUR",
            "c_Season": "2010/2011",
            "n_EditionID": 18045,
            "c_Edition": "2010/2011",
            "d_EditionStartDate": "/Date(1277762400000+0200)/",
            "d_EditionEndDate": "/Date(1309384800000+0200)/",
            "n_PersonNatioGeoID": 2201,
            "n_TeamID": 2,
            "c_Team": "Ajax",
            "c_TeamShort": "AJA",
            "n_TeamNatioGeoID": 2201,
            "c_TeamNatio": "Nederland",
            "c_TeamNatioShort": "NED",
            "n_FunctionType": 8,
            "c_Function": "Aanvaller",
            "c_FunctionShort": "A",
            "n_FunctionCode": 8,
            "n_DateSort": 20100701,
            "n_Matches": 0,
            "n_MatchesStart": 0,
            "n_MatchesOut": 0,
            "n_MatchesIn": 0,
            "n_MinutesPlayed": 0,
            "n_Goals": 0,
            "n_OwnGoals": 0,
            "n_Assists": null,
            "n_CardsRedDirect": 0,
            "n_CardsRed2Yellow": 0,
            "n_CardsRed": 0,
            "n_CardsYellow": 0
        },
        {
            "n_CompetitionID": 43,
            "n_CompetitionLevel": 0,
            "c_Competition": "UEFA Europa League",
            "c_CompetitionShort": "Eur. League",
            "n_CompetitionNatioGeoID": 2101,
            "c_CompetitionNatio": "Europa",
            "c_CompetitionNatioShort": "EUR",
            "c_Season": "2010/2011",
            "n_EditionID": 18046,
            "c_Edition": "2010/2011",
            "d_EditionStartDate": "/Date(1277935200000+0200)/",
            "d_EditionEndDate": "/Date(1309212000000+0200)/",
            "n_PersonNatioGeoID": 2201,
            "n_TeamID": 2,
            "c_Team": "Ajax",
            "c_TeamShort": "AJA",
            "n_TeamNatioGeoID": 2201,
            "c_TeamNatio": "Nederland",
            "c_TeamNatioShort": "NED",
            "n_FunctionType": 8,
            "c_Function": "Aanvaller",
            "c_FunctionShort": "A",
            "n_FunctionCode": 8,
            "n_DateSort": 20100701,
            "n_Matches": 3,
            "n_MatchesStart": 0,
            "n_MatchesOut": 0,
            "n_MatchesIn": 3,
            "n_MinutesPlayed": 61,
            "n_Goals": 0,
            "n_OwnGoals": 0,
            "n_Assists": null,
            "n_CardsRedDirect": 0,
            "n_CardsRed2Yellow": 0,
            "n_CardsRed": 0,
            "n_CardsYellow": 0
        },
        {
            "n_CompetitionID": 41,
            "n_CompetitionLevel": 0,
            "c_Competition": "UEFA Champions League",
            "c_CompetitionShort": "Ch. League",
            "n_CompetitionNatioGeoID": 2101,
            "c_CompetitionNatio": "Europa",
            "c_CompetitionNatioShort": "EUR",
            "c_Season": "2011/2012",
            "n_EditionID": 18772,
            "c_Edition": "2011/2012",
            "d_EditionStartDate": "/Date(1309125600000+0200)/",
            "d_EditionEndDate": "/Date(1341007200000+0200)/",
            "n_PersonNatioGeoID": 4317,
            "n_TeamID": 2,
            "c_Team": "Ajax",
            "c_TeamShort": "AJA",
            "n_TeamNatioGeoID": 2201,
            "c_TeamNatio": "Nederland",
            "c_TeamNatioShort": "NED",
            "n_FunctionType": 8,
            "c_Function": "Aanvaller",
            "c_FunctionShort": "A",
            "n_FunctionCode": 8,
            "n_DateSort": 20100701,
            "n_Matches": 0,
            "n_MatchesStart": 0,
            "n_MatchesOut": 0,
            "n_MatchesIn": 0,
            "n_MinutesPlayed": 0,
            "n_Goals": 0,
            "n_OwnGoals": 0,
            "n_Assists": null,
            "n_CardsRedDirect": 0,
            "n_CardsRed2Yellow": 0,
            "n_CardsRed": 0,
            "n_CardsYellow": 0
        },
        {
            "n_CompetitionID": 43,
            "n_CompetitionLevel": 0,
            "c_Competition": "UEFA Europa League",
            "c_CompetitionShort": "Eur. League",
            "n_CompetitionNatioGeoID": 2101,
            "c_CompetitionNatio": "Europa",
            "c_CompetitionNatioShort": "EUR",
            "c_Season": "2011/2012",
            "n_EditionID": 18773,
            "c_Edition": "2011/2012",
            "d_EditionStartDate": "/Date(1309298400000+0200)/",
            "d_EditionEndDate": "/Date(1341007200000+0200)/",
            "n_PersonNatioGeoID": 4317,
            "n_TeamID": 2,
            "c_Team": "Ajax",
            "c_TeamShort": "AJA",
            "n_TeamNatioGeoID": 2201,
            "c_TeamNatio": "Nederland",
            "c_TeamNatioShort": "NED",
            "n_FunctionType": 8,
            "c_Function": "Aanvaller",
            "c_FunctionShort": "A",
            "n_FunctionCode": 8,
            "n_DateSort": 20100701,
            "n_Matches": 2,
            "n_MatchesStart": 2,
            "n_MatchesOut": 1,
            "n_MatchesIn": 0,
            "n_MinutesPlayed": 169,
            "n_Goals": 1,
            "n_OwnGoals": 0,
            "n_Assists": null,
            "n_CardsRedDirect": 0,
            "n_CardsRed2Yellow": 0,
            "n_CardsRed": 0,
            "n_CardsYellow": 0
        },
        {
            "n_CompetitionID": 43,
            "n_CompetitionLevel": 0,
            "c_Competition": "UEFA Europa League",
            "c_CompetitionShort": "Eur. League",
            "n_CompetitionNatioGeoID": 2101,
            "c_CompetitionNatio": "Europa",
            "c_CompetitionNatioShort": "EUR",
            "c_Season": "2013/2014",
            "n_EditionID": 20626,
            "c_Edition": "2013/2014",
            "d_EditionStartDate": "/Date(1372629600000+0200)/",
            "d_EditionEndDate": "/Date(1404079200000+0200)/",
            "n_PersonNatioGeoID": 4317,
            "n_TeamID": 4120,
            "c_Team": "Spartak Moskou",
            "c_TeamShort": "SPM",
            "n_TeamNatioGeoID": 2204,
            "c_TeamNatio": "Rusland",
            "c_TeamNatioShort": "RUS",
            "n_FunctionType": 8,
            "c_Function": "Aanvaller",
            "c_FunctionShort": "A",
            "n_FunctionCode": 8,
            "n_DateSort": 20130726,
            "n_Matches": 1,
            "n_MatchesStart": 1,
            "n_MatchesOut": 0,
            "n_MatchesIn": 0,
            "n_MinutesPlayed": 90,
            "n_Goals": 1,
            "n_OwnGoals": 0,
            "n_Assists": null,
            "n_CardsRedDirect": 0,
            "n_CardsRed2Yellow": 0,
            "n_CardsRed": 0,
            "n_CardsYellow": 1
        },
        {
            "n_CompetitionID": 41,
            "n_CompetitionLevel": 0,
            "c_Competition": "UEFA Champions League",
            "c_CompetitionShort": "Ch. League",
            "n_CompetitionNatioGeoID": 2101,
            "c_CompetitionNatio": "Europa",
            "c_CompetitionNatioShort": "EUR",
            "c_Season": "2016/2017",
            "n_EditionID": 22330,
            "c_Edition": "2016/2017",
            "d_EditionStartDate": "/Date(1466978400000+0200)/",
            "d_EditionEndDate": "/Date(1498773600000+0200)/",
            "n_PersonNatioGeoID": 4317,
            "n_TeamID": 4020,
            "c_Team": "Besiktas",
            "c_TeamShort": "BES",
            "n_TeamNatioGeoID": 2786,
            "c_TeamNatio": "Turkije",
            "c_TeamNatioShort": "TUR",
            "n_FunctionType": 8,
            "c_Function": "Aanvaller",
            "c_FunctionShort": "A",
            "n_FunctionCode": 8,
            "n_DateSort": 20160701,
            "n_Matches": 0,
            "n_MatchesStart": 0,
            "n_MatchesOut": 0,
            "n_MatchesIn": 0,
            "n_MinutesPlayed": 0,
            "n_Goals": 0,
            "n_OwnGoals": 0,
            "n_Assists": null,
            "n_CardsRedDirect": 0,
            "n_CardsRed2Yellow": 0,
            "n_CardsRed": 0,
            "n_CardsYellow": 0
        },
        {
            "n_CompetitionID": 43,
            "n_CompetitionLevel": 0,
            "c_Competition": "UEFA Europa League",
            "c_CompetitionShort": "Eur. League",
            "n_CompetitionNatioGeoID": 2101,
            "c_CompetitionNatio": "Europa",
            "c_CompetitionNatioShort": "EUR",
            "c_Season": "2016/2017",
            "n_EditionID": 22331,
            "c_Edition": "2016/2017",
            "d_EditionStartDate": "/Date(1466978400000+0200)/",
            "d_EditionEndDate": "/Date(1498773600000+0200)/",
            "n_PersonNatioGeoID": 4317,
            "n_TeamID": 4020,
            "c_Team": "Besiktas",
            "c_TeamShort": "BES",
            "n_TeamNatioGeoID": 2786,
            "c_TeamNatio": "Turkije",
            "c_TeamNatioShort": "TUR",
            "n_FunctionType": 8,
            "c_Function": "Aanvaller",
            "c_FunctionShort": "A",
            "n_FunctionCode": 8,
            "n_DateSort": 20160701,
            "n_Matches": 0,
            "n_MatchesStart": 0,
            "n_MatchesOut": 0,
            "n_MatchesIn": 0,
            "n_MinutesPlayed": 0,
            "n_Goals": 0,
            "n_OwnGoals": 0,
            "n_Assists": null,
            "n_CardsRedDirect": 0,
            "n_CardsRed2Yellow": 0,
            "n_CardsRed": 0,
            "n_CardsYellow": 0
        },
        {
            "n_CompetitionID": 41,
            "n_CompetitionLevel": 0,
            "c_Competition": "UEFA Champions League",
            "c_CompetitionShort": "Ch. League",
            "n_CompetitionNatioGeoID": 2101,
            "c_CompetitionNatio": "Europa",
            "c_CompetitionNatioShort": "EUR",
            "c_Season": "2017/2018",
            "n_EditionID": 22934,
            "c_Edition": "2017/2018",
            "d_EditionStartDate": "/Date(1498428000000+0200)/",
            "d_EditionEndDate": "/Date(1530309600000+0200)/",
            "n_PersonNatioGeoID": 4317,
            "n_TeamID": 4020,
            "c_Team": "Besiktas",
            "c_TeamShort": "BES",
            "n_TeamNatioGeoID": 2786,
            "c_TeamNatio": "Turkije",
            "c_TeamNatioShort": "TUR",
            "n_FunctionType": 8,
            "c_Function": "Aanvaller",
            "c_FunctionShort": "A",
            "n_FunctionCode": 8,
            "n_DateSort": 20160701,
            "n_Matches": 0,
            "n_MatchesStart": 0,
            "n_MatchesOut": 0,
            "n_MatchesIn": 0,
            "n_MinutesPlayed": 0,
            "n_Goals": 0,
            "n_OwnGoals": 0,
            "n_Assists": null,
            "n_CardsRedDirect": 0,
            "n_CardsRed2Yellow": 0,
            "n_CardsRed": 0,
            "n_CardsYellow": 0
        },
        {
            "n_CompetitionID": 43,
            "n_CompetitionLevel": 0,
            "c_Competition": "UEFA Europa League",
            "c_CompetitionShort": "Eur. League",
            "n_CompetitionNatioGeoID": 2101,
            "c_CompetitionNatio": "Europa",
            "c_CompetitionNatioShort": "EUR",
            "c_Season": "2019/2020",
            "n_EditionID": 24184,
            "c_Edition": "2019/2020",
            "d_EditionStartDate": "/Date(1561586400000+0200)/",
            "d_EditionEndDate": "/Date(1593468000000+0200)/",
            "n_PersonNatioGeoID": 4317,
            "n_TeamID": 5112,
            "c_Team": "FC Pyunik",
            "c_TeamShort": "PIU",
            "n_TeamNatioGeoID": 4317,
            "c_TeamNatio": "Armenië",
            "c_TeamNatioShort": "ARM",
            "n_FunctionType": 4,
            "c_Function": "Middenvelder",
            "c_FunctionShort": "M",
            "n_FunctionCode": 4,
            "n_DateSort": 20190701,
            "n_Matches": 0,
            "n_MatchesStart": 0,
            "n_MatchesOut": 0,
            "n_MatchesIn": 0,
            "n_MinutesPlayed": 0,
            "n_Goals": 0,
            "n_OwnGoals": 0,
            "n_Assists": null,
            "n_CardsRedDirect": 0,
            "n_CardsRed2Yellow": 0,
            "n_CardsRed": 0,
            "n_CardsYellow": 0
        }
    ],
    "PlayerInternational": [
        {
            "n_CompetitionID": 10,
            "n_CompetitionLevel": 0,
            "c_Competition": "Europees Kampioenschap Kwalificatie",
            "c_CompetitionShort": "EK Kwal.",
            "n_CompetitionNatioGeoID": 2101,
            "c_CompetitionNatio": "Europa",
            "c_CompetitionNatioShort": "EUR",
            "c_Season": "2012",
            "n_EditionID": 17648,
            "c_Edition": "2012",
            "d_EditionStartDate": "/Date(1281391200000+0200)/",
            "d_EditionEndDate": "/Date(1321311600000+0100)/",
            "n_PersonNatioGeoID": 4317,
            "n_TeamID": 3093,
            "c_Team": "Armenië",
            "c_TeamShort": "ARM",
            "n_TeamNatioGeoID": 4317,
            "c_TeamNatio": "Armenië",
            "c_TeamNatioShort": "ARM",
            "n_FunctionType": 4,
            "c_Function": "Middenvelder",
            "c_FunctionShort": "M",
            "n_FunctionCode": 4,
            "n_DateSort": 20111004,
            "n_Matches": 0,
            "n_MatchesStart": 0,
            "n_MatchesOut": 0,
            "n_MatchesIn": 0,
            "n_MinutesPlayed": 0,
            "n_Goals": 0,
            "n_OwnGoals": 0,
            "n_Assists": null,
            "n_CardsRedDirect": 0,
            "n_CardsRed2Yellow": 0,
            "n_CardsRed": 0,
            "n_CardsYellow": 0
        },
        {
            "n_CompetitionID": 11,
            "n_CompetitionLevel": 0,
            "c_Competition": "Vriendschappelijk",
            "c_CompetitionShort": "Vriendsch.",
            "n_CompetitionNatioGeoID": 0,
            "c_CompetitionNatio": null,
            "c_CompetitionNatioShort": null,
            "c_Season": "2012",
            "n_EditionID": 19204,
            "c_Edition": "2012",
            "d_EditionStartDate": "/Date(1325372400000+0100)/",
            "d_EditionEndDate": "/Date(1356908400000+0100)/",
            "n_PersonNatioGeoID": 4317,
            "n_TeamID": 3093,
            "c_Team": "Armenië",
            "c_TeamShort": "ARM",
            "n_TeamNatioGeoID": 4317,
            "c_TeamNatio": "Armenië",
            "c_TeamNatioShort": "ARM",
            "n_FunctionType": 4,
            "c_Function": "Middenvelder",
            "c_FunctionShort": "M",
            "n_FunctionCode": 4,
            "n_DateSort": 20111004,
            "n_Matches": 0,
            "n_MatchesStart": 0,
            "n_MatchesOut": 0,
            "n_MatchesIn": 0,
            "n_MinutesPlayed": 0,
            "n_Goals": 2,
            "n_OwnGoals": 0,
            "n_Assists": null,
            "n_CardsRedDirect": 0,
            "n_CardsRed2Yellow": 0,
            "n_CardsRed": 0,
            "n_CardsYellow": 0
        },
        {
            "n_CompetitionID": 108,
            "n_CompetitionLevel": 0,
            "c_Competition": "Wereldkampioenschap Kwalificatie UEFA",
            "c_CompetitionShort": "WK Kwal. UEFA",
            "n_CompetitionNatioGeoID": 2101,
            "c_CompetitionNatio": "Europa",
            "c_CompetitionNatioShort": "EUR",
            "c_Season": "2014",
            "n_EditionID": 19031,
            "c_Edition": "2014",
            "d_EditionStartDate": "/Date(1346968800000+0200)/",
            "d_EditionEndDate": "/Date(1384815600000+0100)/",
            "n_PersonNatioGeoID": 4317,
            "n_TeamID": 3093,
            "c_Team": "Armenië",
            "c_TeamShort": "ARM",
            "n_TeamNatioGeoID": 4317,
            "c_TeamNatio": "Armenië",
            "c_TeamNatioShort": "ARM",
            "n_FunctionType": 4,
            "c_Function": "Middenvelder",
            "c_FunctionShort": "M",
            "n_FunctionCode": 4,
            "n_DateSort": 20111004,
            "n_Matches": 10,
            "n_MatchesStart": 9,
            "n_MatchesOut": 5,
            "n_MatchesIn": 1,
            "n_MinutesPlayed": 707,
            "n_Goals": 2,
            "n_OwnGoals": 0,
            "n_Assists": null,
            "n_CardsRedDirect": 0,
            "n_CardsRed2Yellow": 0,
            "n_CardsRed": 0,
            "n_CardsYellow": 1
        },
        {
            "n_CompetitionID": 11,
            "n_CompetitionLevel": 0,
            "c_Competition": "Vriendschappelijk",
            "c_CompetitionShort": "Vriendsch.",
            "n_CompetitionNatioGeoID": 0,
            "c_CompetitionNatio": null,
            "c_CompetitionNatioShort": null,
            "c_Season": "2013",
            "n_EditionID": 20376,
            "c_Edition": "2013",
            "d_EditionStartDate": "/Date(1356994800000+0100)/",
            "d_EditionEndDate": "/Date(1388444400000+0100)/",
            "n_PersonNatioGeoID": 4317,
            "n_TeamID": 3093,
            "c_Team": "Armenië",
            "c_TeamShort": "ARM",
            "n_TeamNatioGeoID": 4317,
            "c_TeamNatio": "Armenië",
            "c_TeamNatioShort": "ARM",
            "n_FunctionType": 4,
            "c_Function": "Middenvelder",
            "c_FunctionShort": "M",
            "n_FunctionCode": 4,
            "n_DateSort": 20111004,
            "n_Matches": 0,
            "n_MatchesStart": 0,
            "n_MatchesOut": 0,
            "n_MatchesIn": 0,
            "n_MinutesPlayed": 0,
            "n_Goals": 0,
            "n_OwnGoals": 0,
            "n_Assists": null,
            "n_CardsRedDirect": 0,
            "n_CardsRed2Yellow": 0,
            "n_CardsRed": 0,
            "n_CardsYellow": 0
        },
        {
            "n_CompetitionID": 11,
            "n_CompetitionLevel": 0,
            "c_Competition": "Vriendschappelijk",
            "c_CompetitionShort": "Vriendsch.",
            "n_CompetitionNatioGeoID": 0,
            "c_CompetitionNatio": null,
            "c_CompetitionNatioShort": null,
            "c_Season": "2014",
            "n_EditionID": 20981,
            "c_Edition": "2014",
            "d_EditionStartDate": "/Date(1388530800000+0100)/",
            "d_EditionEndDate": "/Date(1419980400000+0100)/",
            "n_PersonNatioGeoID": 4317,
            "n_TeamID": 3093,
            "c_Team": "Armenië",
            "c_TeamShort": "ARM",
            "n_TeamNatioGeoID": 4317,
            "c_TeamNatio": "Armenië",
            "c_TeamNatioShort": "ARM",
            "n_FunctionType": 4,
            "c_Function": "Middenvelder",
            "c_FunctionShort": "M",
            "n_FunctionCode": 4,
            "n_DateSort": 0,
            "n_Matches": 0,
            "n_MatchesStart": 0,
            "n_MatchesOut": 0,
            "n_MatchesIn": 0,
            "n_MinutesPlayed": 0,
            "n_Goals": 0,
            "n_OwnGoals": 0,
            "n_Assists": null,
            "n_CardsRedDirect": 0,
            "n_CardsRed2Yellow": 0,
            "n_CardsRed": 0,
            "n_CardsYellow": 0
        },
        {
            "n_CompetitionID": 10,
            "n_CompetitionLevel": 0,
            "c_Competition": "Europees Kampioenschap Kwalificatie",
            "c_CompetitionShort": "EK Kwal.",
            "n_CompetitionNatioGeoID": 2101,
            "c_CompetitionNatio": "Europa",
            "c_CompetitionNatioShort": "EUR",
            "c_Season": "2016",
            "n_EditionID": 21099,
            "c_Edition": "2016",
            "d_EditionStartDate": "/Date(1409954400000+0200)/",
            "d_EditionEndDate": "/Date(1447801200000+0100)/",
            "n_PersonNatioGeoID": 4317,
            "n_TeamID": 3093,
            "c_Team": "Armenië",
            "c_TeamShort": "ARM",
            "n_TeamNatioGeoID": 4317,
            "c_TeamNatio": "Armenië",
            "c_TeamNatioShort": "ARM",
            "n_FunctionType": 4,
            "c_Function": "Middenvelder",
            "c_FunctionShort": "M",
            "n_FunctionCode": 4,
            "n_DateSort": 20140902,
            "n_Matches": 4,
            "n_MatchesStart": 1,
            "n_MatchesOut": 1,
            "n_MatchesIn": 3,
            "n_MinutesPlayed": 142,
            "n_Goals": 0,
            "n_OwnGoals": 0,
            "n_Assists": null,
            "n_CardsRedDirect": 0,
            "n_CardsRed2Yellow": 0,
            "n_CardsRed": 0,
            "n_CardsYellow": 0
        },
        {
            "n_CompetitionID": 11,
            "n_CompetitionLevel": 0,
            "c_Competition": "Vriendschappelijk",
            "c_CompetitionShort": "Vriendsch.",
            "n_CompetitionNatioGeoID": 0,
            "c_CompetitionNatio": null,
            "c_CompetitionNatioShort": null,
            "c_Season": "2015",
            "n_EditionID": 21520,
            "c_Edition": "2015",
            "d_EditionStartDate": "/Date(1420066800000+0100)/",
            "d_EditionEndDate": "/Date(1451516400000+0100)/",
            "n_PersonNatioGeoID": 4317,
            "n_TeamID": 3093,
            "c_Team": "Armenië",
            "c_TeamShort": "ARM",
            "n_TeamNatioGeoID": 4317,
            "c_TeamNatio": "Armenië",
            "c_TeamNatioShort": "ARM",
            "n_FunctionType": 4,
            "c_Function": "Middenvelder",
            "c_FunctionShort": "M",
            "n_FunctionCode": 4,
            "n_DateSort": 20140902,
            "n_Matches": 1,
            "n_MatchesStart": 0,
            "n_MatchesOut": 0,
            "n_MatchesIn": 1,
            "n_MinutesPlayed": 37,
            "n_Goals": 0,
            "n_OwnGoals": 0,
            "n_Assists": null,
            "n_CardsRedDirect": 0,
            "n_CardsRed2Yellow": 0,
            "n_CardsRed": 0,
            "n_CardsYellow": 0
        },
        {
            "n_CompetitionID": 11,
            "n_CompetitionLevel": 0,
            "c_Competition": "Vriendschappelijk",
            "c_CompetitionShort": "Vriendsch.",
            "n_CompetitionNatioGeoID": 0,
            "c_CompetitionNatio": null,
            "c_CompetitionNatioShort": null,
            "c_Season": "2016",
            "n_EditionID": 22112,
            "c_Edition": "2016",
            "d_EditionStartDate": "/Date(1451602800000+0100)/",
            "d_EditionEndDate": "/Date(1483138800000+0100)/",
            "n_PersonNatioGeoID": 4317,
            "n_TeamID": 3093,
            "c_Team": "Armenië",
            "c_TeamShort": "ARM",
            "n_TeamNatioGeoID": 4317,
            "c_TeamNatio": "Armenië",
            "c_TeamNatioShort": "ARM",
            "n_FunctionType": 4,
            "c_Function": "Middenvelder",
            "c_FunctionShort": "M",
            "n_FunctionCode": 4,
            "n_DateSort": 20140902,
            "n_Matches": 1,
            "n_MatchesStart": 0,
            "n_MatchesOut": 0,
            "n_MatchesIn": 1,
            "n_MinutesPlayed": 45,
            "n_Goals": 0,
            "n_OwnGoals": 0,
            "n_Assists": null,
            "n_CardsRedDirect": 0,
            "n_CardsRed2Yellow": 0,
            "n_CardsRed": 0,
            "n_CardsYellow": 0
        },
        {
            "n_CompetitionID": 108,
            "n_CompetitionLevel": 0,
            "c_Competition": "Wereldkampioenschap Kwalificatie UEFA",
            "c_CompetitionShort": "WK Kwal. UEFA",
            "n_CompetitionNatioGeoID": 2101,
            "c_CompetitionNatio": "Europa",
            "c_CompetitionNatioShort": "EUR",
            "c_Season": "2018",
            "n_EditionID": 21981,
            "c_Edition": "2018",
            "d_EditionStartDate": "/Date(1472853600000+0200)/",
            "d_EditionEndDate": "/Date(1510700400000+0100)/",
            "n_PersonNatioGeoID": 4317,
            "n_TeamID": 3093,
            "c_Team": "Armenië",
            "c_TeamShort": "ARM",
            "n_TeamNatioGeoID": 4317,
            "c_TeamNatio": "Armenië",
            "c_TeamNatioShort": "ARM",
            "n_FunctionType": 4,
            "c_Function": "Middenvelder",
            "c_FunctionShort": "M",
            "n_FunctionCode": 4,
            "n_DateSort": 20140902,
            "n_Matches": 6,
            "n_MatchesStart": 3,
            "n_MatchesOut": 3,
            "n_MatchesIn": 3,
            "n_MinutesPlayed": 231,
            "n_Goals": 1,
            "n_OwnGoals": 0,
            "n_Assists": null,
            "n_CardsRedDirect": 0,
            "n_CardsRed2Yellow": 0,
            "n_CardsRed": 0,
            "n_CardsYellow": 1
        },
        {
            "n_CompetitionID": 11,
            "n_CompetitionLevel": 0,
            "c_Competition": "Vriendschappelijk",
            "c_CompetitionShort": "Vriendsch.",
            "n_CompetitionNatioGeoID": 0,
            "c_CompetitionNatio": null,
            "c_CompetitionNatioShort": null,
            "c_Season": "2017",
            "n_EditionID": 22658,
            "c_Edition": "2017",
            "d_EditionStartDate": "/Date(1483225200000+0100)/",
            "d_EditionEndDate": "/Date(1514674800000+0100)/",
            "n_PersonNatioGeoID": 4317,
            "n_TeamID": 3093,
            "c_Team": "Armenië",
            "c_TeamShort": "ARM",
            "n_TeamNatioGeoID": 4317,
            "c_TeamNatio": "Armenië",
            "c_TeamNatioShort": "ARM",
            "n_FunctionType": 4,
            "c_Function": "Middenvelder",
            "c_FunctionShort": "M",
            "n_FunctionCode": 4,
            "n_DateSort": 20140902,
            "n_Matches": 0,
            "n_MatchesStart": 0,
            "n_MatchesOut": 0,
            "n_MatchesIn": 0,
            "n_MinutesPlayed": 0,
            "n_Goals": 1,
            "n_OwnGoals": 0,
            "n_Assists": null,
            "n_CardsRedDirect": 0,
            "n_CardsRed2Yellow": 0,
            "n_CardsRed": 0,
            "n_CardsYellow": 0
        },
        {
            "n_CompetitionID": 11,
            "n_CompetitionLevel": 0,
            "c_Competition": "Vriendschappelijk",
            "c_CompetitionShort": "Vriendsch.",
            "n_CompetitionNatioGeoID": 0,
            "c_CompetitionNatio": null,
            "c_CompetitionNatioShort": null,
            "c_Season": "2018",
            "n_EditionID": 23258,
            "c_Edition": "2018",
            "d_EditionStartDate": "/Date(1514761200000+0100)/",
            "d_EditionEndDate": "/Date(1546297140000+0100)/",
            "n_PersonNatioGeoID": 4317,
            "n_TeamID": 3093,
            "c_Team": "Armenië",
            "c_TeamShort": "ARM",
            "n_TeamNatioGeoID": 4317,
            "c_TeamNatio": "Armenië",
            "c_TeamNatioShort": "ARM",
            "n_FunctionType": 4,
            "c_Function": "Middenvelder",
            "c_FunctionShort": "M",
            "n_FunctionCode": 4,
            "n_DateSort": 20140902,
            "n_Matches": 0,
            "n_MatchesStart": 0,
            "n_MatchesOut": 0,
            "n_MatchesIn": 0,
            "n_MinutesPlayed": 0,
            "n_Goals": 0,
            "n_OwnGoals": 0,
            "n_Assists": null,
            "n_CardsRedDirect": 0,
            "n_CardsRed2Yellow": 0,
            "n_CardsRed": 0,
            "n_CardsYellow": 0
        },
        {
            "n_CompetitionID": 961,
            "n_CompetitionLevel": 0,
            "c_Competition": "UEFA Nations League",
            "c_CompetitionShort": null,
            "n_CompetitionNatioGeoID": 2101,
            "c_CompetitionNatio": "Europa",
            "c_CompetitionNatioShort": "EUR",
            "c_Season": "2018/2019",
            "n_EditionID": 23384,
            "c_Edition": "2018/2019",
            "d_EditionStartDate": "/Date(1536098400000+0200)/",
            "d_EditionEndDate": "/Date(1560117600000+0200)/",
            "n_PersonNatioGeoID": 4317,
            "n_TeamID": 3093,
            "c_Team": "Armenië",
            "c_TeamShort": "ARM",
            "n_TeamNatioGeoID": 4317,
            "c_TeamNatio": "Armenië",
            "c_TeamNatioShort": "ARM",
            "n_FunctionType": 4,
            "c_Function": "Middenvelder",
            "c_FunctionShort": "M",
            "n_FunctionCode": 4,
            "n_DateSort": 20140902,
            "n_Matches": 2,
            "n_MatchesStart": 1,
            "n_MatchesOut": 1,
            "n_MatchesIn": 1,
            "n_MinutesPlayed": 106,
            "n_Goals": 0,
            "n_OwnGoals": 0,
            "n_Assists": null,
            "n_CardsRedDirect": 0,
            "n_CardsRed2Yellow": 0,
            "n_CardsRed": 0,
            "n_CardsYellow": 0
        },
        {
            "n_CompetitionID": 11,
            "n_CompetitionLevel": 0,
            "c_Competition": "Vriendschappelijk",
            "c_CompetitionShort": "Vriendsch.",
            "n_CompetitionNatioGeoID": 0,
            "c_CompetitionNatio": null,
            "c_CompetitionNatioShort": null,
            "c_Season": "2019",
            "n_EditionID": 23923,
            "c_Edition": "2019",
            "d_EditionStartDate": "/Date(1546297200000+0100)/",
            "d_EditionEndDate": "/Date(1577746800000+0100)/",
            "n_PersonNatioGeoID": 4317,
            "n_TeamID": 3093,
            "c_Team": "Armenië",
            "c_TeamShort": "ARM",
            "n_TeamNatioGeoID": 4317,
            "c_TeamNatio": "Armenië",
            "c_TeamNatioShort": "ARM",
            "n_FunctionType": 4,
            "c_Function": "Middenvelder",
            "c_FunctionShort": "M",
            "n_FunctionCode": 4,
            "n_DateSort": 20140902,
            "n_Matches": 0,
            "n_MatchesStart": 0,
            "n_MatchesOut": 0,
            "n_MatchesIn": 0,
            "n_MinutesPlayed": 0,
            "n_Goals": 0,
            "n_OwnGoals": 0,
            "n_Assists": null,
            "n_CardsRedDirect": 0,
            "n_CardsRed2Yellow": 0,
            "n_CardsRed": 0,
            "n_CardsYellow": 0
        },
        {
            "n_CompetitionID": 10,
            "n_CompetitionLevel": 0,
            "c_Competition": "EK-kwalificatie",
            "c_CompetitionShort": "EK Kwal.",
            "n_CompetitionNatioGeoID": 2101,
            "c_CompetitionNatio": "Europa",
            "c_CompetitionNatioShort": "EUR",
            "c_Season": "2021",
            "n_EditionID": 24006,
            "c_Edition": "2021",
            "d_EditionStartDate": "/Date(1553036400000+0100)/",
            "d_EditionEndDate": "/Date(1591826400000+0200)/",
            "n_PersonNatioGeoID": 4317,
            "n_TeamID": 3093,
            "c_Team": "Armenië",
            "c_TeamShort": "ARM",
            "n_TeamNatioGeoID": 4317,
            "c_TeamNatio": "Armenië",
            "c_TeamNatioShort": "ARM",
            "n_FunctionType": 4,
            "c_Function": "Middenvelder",
            "c_FunctionShort": "M",
            "n_FunctionCode": 4,
            "n_DateSort": 20140902,
            "n_Matches": 4,
            "n_MatchesStart": 1,
            "n_MatchesOut": 1,
            "n_MatchesIn": 3,
            "n_MinutesPlayed": 106,
            "n_Goals": 0,
            "n_OwnGoals": 0,
            "n_Assists": null,
            "n_CardsRedDirect": 0,
            "n_CardsRed2Yellow": 0,
            "n_CardsRed": 0,
            "n_CardsYellow": 0
        },
        {
            "n_CompetitionID": 11,
            "n_CompetitionLevel": 0,
            "c_Competition": "Vriendschappelijk",
            "c_CompetitionShort": "Vriendsch.",
            "n_CompetitionNatioGeoID": 0,
            "c_CompetitionNatio": null,
            "c_CompetitionNatioShort": null,
            "c_Season": "2020",
            "n_EditionID": 24602,
            "c_Edition": "2020",
            "d_EditionStartDate": "/Date(1577833200000+0100)/",
            "d_EditionEndDate": "/Date(1609369200000+0100)/",
            "n_PersonNatioGeoID": 4317,
            "n_TeamID": 3093,
            "c_Team": "Armenië",
            "c_TeamShort": "ARM",
            "n_TeamNatioGeoID": 4317,
            "c_TeamNatio": "Armenië",
            "c_TeamNatioShort": "ARM",
            "n_FunctionType": 4,
            "c_Function": "Middenvelder",
            "c_FunctionShort": "M",
            "n_FunctionCode": 4,
            "n_DateSort": 20140902,
            "n_Matches": 0,
            "n_MatchesStart": 0,
            "n_MatchesOut": 0,
            "n_MatchesIn": 0,
            "n_MinutesPlayed": 0,
            "n_Goals": 0,
            "n_OwnGoals": 0,
            "n_Assists": null,
            "n_CardsRedDirect": 0,
            "n_CardsRed2Yellow": 0,
            "n_CardsRed": 0,
            "n_CardsYellow": 0
        }
    ]
}